alu.vhd
library ieee;
use ieee.std_logic_1164.all;
use ieee.numeric_std.all;

entity alu is
    port(
        x, y: in unsigned(13 downto 0);
        select_op: in unsigned(2 downto 0);
        output: out unsigned(13 downto 0);
        carry : out std_logic;
        zero : out std_logic
    );
    signal is_odd: unsigned(13 downto 0);
end entity;

architecture a_alu of alu is
begin
    is_odd <=
    "00000000000001" when x(0) = '1' else
    "00000000000000" when x(0) = '0' else
    "00000000000000";
    
    output <=
    x+y when select_op="000" else
    x-y when select_op="001" else
    x AND y when select_op="010" else
    x XOR y when select_op="011" else
    NOT x when select_op="100" else
    x OR y when select_op="101" else
    is_odd when select_op="110" else
    "00000000000000";

    zero <= '1' when x-y = "00000000000000" else '0';
    
    carry <= '1' when y > x else '0';
    
end architecture;

-- subtração

alu_tb.vhd
library ieee;
use ieee.std_logic_1164.all;
use ieee.numeric_std.all;

entity alu_tb is
end;

architecture a_alu_tb of alu_tb is
    component alu is
        port
        (
            x         : IN unsigned (13 downto 0);
            y         : IN unsigned (13 downto 0);
            select_op : IN unsigned (2 downto 0);
            output    : OUT unsigned (13 downto 0);
            carry : OUT std_logic;
            zero : OUT std_logic
            
        );
    end component;
    signal x, y, output: unsigned(13 downto 0);
    signal select_op: unsigned(2 downto 0);
    signal zero, carry: std_logic;

begin
    uut: alu
    port map
    (
        x         => x,
        y         => y,
        select_op => select_op,
        output    => output,
        carry => carry,
        zero => zero
    );


    process
    begin
        select_op <= "000"; --SUM
        x <= "00000010000001";
        y <= "11111101111110";
        wait for 50 ns;
        select_op <= "001"; --SUB
        x <= "00000010000001";
        y <= "11111101111110";
        wait for 50 ns;
        select_op <= "010"; --AND
        x <= "00000010000001";
        y <= "11111101111110";
        wait for 50 ns;
        select_op <= "011"; --XOR
        x <= "00000010000001";
        y <= "11111101111101";
        wait for 50 ns;
        select_op <= "100"; --NOT
        x <= "00000010000001";
        y <= "11111101111110";
        wait for 50 ns;
        select_op <= "101"; --OR
        x <= "00000010000001";
        y <= "11111101111110";
        wait for 50 ns;
        select_op <= "110"; --IS ODD
        x <= "00000010000001";
        wait for 50 ns;
        x <= "00000000000001";
        y <= "00000000000001";
        wait for 50 ns;
        x <= "00000000000010";
        y <= "00000000000001";
        wait for 50 ns;
        x <= "00000000000010";
        y <= "00000000000011";
        wait for 50 ns;
        wait;
    end process;
end architecture;

alu_tb.vcd
$date
  Thu May 26 21:20:58 2022
$end
$version
  GHDL v0
$end
$timescale
  1 fs
$end
$scope module standard $end
$upscope $end
$scope module textio $end
$upscope $end
$scope module std_logic_1164 $end
$upscope $end
$scope module numeric_std $end
$upscope $end
$scope module alu_tb $end
$var reg 14 ! x[13:0] $end
$var reg 14 " y[13:0] $end
$var reg 14 # output[13:0] $end
$var reg 3 $ select_op[2:0] $end
$var reg 1 % zero $end
$var reg 1 & carry $end
$scope module uut $end
$var reg 14 ' x[13:0] $end
$var reg 14 ( y[13:0] $end
$var reg 3 ) select_op[2:0] $end
$var reg 14 * output[13:0] $end
$var reg 1 + carry $end
$var reg 1 , zero $end
$var reg 14 - is_odd[13:0] $end
$upscope $end
$upscope $end
$enddefinitions $end
#0
b00000010000001 !
b11111101111110 "
b11111111111111 #
b000 $
0%
1&
b00000010000001 '
b11111101111110 (
b000 )
b11111111111111 *
1+
0,
b00000000000001 -
#50000000
b00000100000011 #
b001 $
b001 )
b00000100000011 *
#100000000
b00000000000000 #
b010 $
b010 )
b00000000000000 *
#150000000
b11111101111101 "
b11111111111100 #
b011 $
b11111101111101 (
b011 )
b11111111111100 *
#200000000
b11111101111110 "
b11111101111110 #
b100 $
b11111101111110 (
b100 )
b11111101111110 *
#250000000
b11111111111111 #
b101 $
b101 )
b11111111111111 *
#300000000
b00000000000001 #
b110 $
b110 )
b00000000000001 *
#350000000
b00000000000001 !
b00000000000001 "
1%
0&
b00000000000001 '
b00000000000001 (
0+
1,
#400000000
b00000000000010 !
b00000000000000 #
0%
b00000000000010 '
b00000000000000 *
0,
b00000000000000 -
#450000000
b00000000000011 "
1&
b00000000000011 (
1+
