mux8x1.vhd
library ieee;
use ieee.std_logic_1164.all;

entity mux8x1 is
    port( sel0, sel1, sel2: in std_logic;
        i0, i1, i2, i3, i4, i5, i6, i7: in std_logic;
        output: out std_logic
    );
end entity;

architecture a_mux8x1 of mux8x1 is
begin
    output <=
    i0 when sel2='0' and sel1='0' and sel0='0' else
    i1 when sel2='0' and sel1='0' and sel0='1' else
    i2 when sel2='0' and sel1='1' and sel0='0' else
    i3 when sel2='0' and sel1='1' and sel0='1' else
    i4 when sel2='1' and sel1='0' and sel0='0' else
    i5 when sel2='1' and sel1='0' and sel0='1' else
    i6 when sel2='1' and sel1='1' and sel0='0' else
    i7 when sel2='1' and sel1='1' and sel0='1' else
    '0';
end architecture;

mux8x1_tb.vhd
library ieee;
use ieee.std_logic_1164.all;

entity mux8x1_tb is
end;

architecture a_mux8x1_tb of mux8x1_tb is
    component mux8x1 is
        port
        (
            sel0   : in std_logic ;
            sel1   : in std_logic ;
            sel2   : in std_logic ;
            i0     : in std_logic ;
            i1     : in std_logic ;
            i2     : in std_logic ;
            i3     : in std_logic ;
            i4     : in std_logic ;
            i5     : in std_logic ;
            i6     : in std_logic ;
            i7     : in std_logic ;
            output : out std_logic
        );
    end component;
    signal sel2, sel1, sel0, i0, i1, i2, i3, i4, i5, i6, i7, output: std_logic;
begin
    uut: mux8x1
    port map
    (
        sel0   => sel0,
        sel1   => sel1,
        sel2   => sel2,
        i0     => i0,
        i1     => i1,
        i2     => i2,
        i3     => i3,
        i4     => i4,
        i5     => i5,
        i6     => i6,
        i7     => i7,
        output => output
    );

    
    process
    begin
        i0 <= '1';
        i1 <= '0';
        i2 <= '1';
        i3 <= '0';
        i4 <= '1';
        i5 <= '0';
        i6 <= '1';
        i7 <= '0';
        sel0 <= '0';
        sel1 <= '0';
        sel2 <= '0';
        wait for 50 ns;
        sel0 <= '1';
        sel1 <= '0';
        sel2 <= '0';
        wait for 50 ns;
        sel0 <= '0';
        sel1 <= '1';
        sel2 <= '0';
        wait for 50 ns;
        sel0 <= '1';
        sel1 <= '1';
        sel2 <= '0';
        wait for 50 ns;
        sel0 <= '0';
        sel1 <= '0';
        sel2 <= '1';
        wait for 50 ns;
        sel0 <= '1';
        sel1 <= '0';
        sel2 <= '1';
        wait for 50 ns;
        sel0 <= '0';
        sel1 <= '1';
        sel2 <= '1';
        wait for 50 ns;
        sel0 <= '1';
        sel1 <= '1';
        sel2 <= '1';
        wait for 50 ns;
        wait;
    end process;
end architecture;

mux8x1_tb.vcd
$date
  Thu Apr  7 16:34:01 2022
$end
$version
  GHDL v0
$end
$timescale
  1 fs
$end
$scope module standard $end
$upscope $end
$scope module std_logic_1164 $end
$upscope $end
$scope module mux8x1_tb $end
$var reg 1 ! sel2 $end
$var reg 1 " sel1 $end
$var reg 1 # sel0 $end
$var reg 1 $ i0 $end
$var reg 1 % i1 $end
$var reg 1 & i2 $end
$var reg 1 ' i3 $end
$var reg 1 ( i4 $end
$var reg 1 ) i5 $end
$var reg 1 * i6 $end
$var reg 1 + i7 $end
$var reg 1 , output $end
$scope module uut $end
$var reg 1 - sel0 $end
$var reg 1 . sel1 $end
$var reg 1 / sel2 $end
$var reg 1 0 i0 $end
$var reg 1 1 i1 $end
$var reg 1 2 i2 $end
$var reg 1 3 i3 $end
$var reg 1 4 i4 $end
$var reg 1 5 i5 $end
$var reg 1 6 i6 $end
$var reg 1 7 i7 $end
$var reg 1 8 output $end
$upscope $end
$upscope $end
$enddefinitions $end
#0
0!
0"
0#
1$
0%
1&
0'
1(
0)
1*
0+
1,
0-
0.
0/
10
01
12
03
14
05
16
07
18
#50000000
1#
0,
1-
08
#100000000
1"
0#
1,
0-
1.
18
#150000000
1#
0,
1-
08
#200000000
1!
0"
0#
1,
0-
0.
1/
18
#250000000
1#
0,
1-
08
#300000000
1"
0#
1,
0-
1.
18
#350000000
1#
0,
1-
08
