reg14bits.vhd
library ieee;
use ieee.std_logic_1164.all;
use ieee.numeric_std.all;

entity reg14bits is
    port(
        clk : in std_logic;
        rst : in std_logic;
        wr_en : in std_logic;
        data_in : in unsigned(13 downto 0);
        data_out : out unsigned(13 downto 0)
    );
end entity;

architecture a_reg14bits of reg14bits is
    signal reg: unsigned(13 downto 0);
begin
    process(clk,rst,wr_en)
    begin
        if rst='1' then
            reg <= "00000000000000";
        elsif wr_en='1' then
            if rising_edge(clk) then
                reg <= data_in;
            end if;
        end if;
    end process;

    data_out <= reg;
end architecture;

reg_bank.vhd
library ieee;
use ieee.std_logic_1164.all;
use ieee.numeric_std.all;

entity reg_bank is
    port(
        clk, rst, wr_en : in std_logic;
        select_reg_a, select_reg_b, select_write_reg : in unsigned(2 downto 0);
        write_data: in unsigned(13 downto 0);
        reg_a, reg_b : out unsigned(13 downto 0)
    );
end entity;

architecture a_reg_bank of reg_bank is
    component reg14bits is
        port
        (
            clk      : IN std_logic ;
            rst      : IN std_logic ;
            wr_en    : IN std_logic ;
            data_in  : IN unsigned (13 downto 0);
            data_out : OUT unsigned (13 downto 0)
        );
    end component;

    signal wr_en_1, wr_en_2, wr_en_3, wr_en_4, wr_en_5, wr_en_6, wr_en_7 : std_logic;
    signal data_out_reg_1, data_out_reg_2, data_out_reg_3, data_out_reg_4, data_out_reg_5, data_out_reg_6, data_out_reg_7: unsigned(13 downto 0);
begin
   reg1: reg14bits
    port map
    (
        clk      => clk,
        rst      => rst,
        wr_en    => wr_en_1,
        data_in  => write_data,
        data_out => data_out_reg_1
    );

    reg2: reg14bits
    port map
    (
        clk      => clk,
        rst      => rst,
        wr_en    => wr_en_2,
        data_in  => write_data,
        data_out => data_out_reg_2
    );

    reg3: reg14bits
    port map
    (
        clk      => clk,
        rst      => rst,
        wr_en    => wr_en_3,
        data_in  => write_data,
        data_out => data_out_reg_3
    );

    reg4: reg14bits
    port map
    (
        clk      => clk,
        rst      => rst,
        wr_en    => wr_en_4,
        data_in  => write_data,
        data_out => data_out_reg_4
    );

    reg5: reg14bits
    port map
    (
        clk      => clk,
        rst      => rst,
        wr_en    => wr_en_5,
        data_in  => write_data,
        data_out => data_out_reg_5
    );

    reg6: reg14bits
    port map
    (
        clk      => clk,
        rst      => rst,
        wr_en    => wr_en_6,
        data_in  => write_data,
        data_out => data_out_reg_6
    );

    reg7: reg14bits
    port map
    (
        clk      => clk,
        rst      => rst,
        wr_en    => wr_en_7,
        data_in  => write_data,
        data_out => data_out_reg_7
    );

   
    wr_en_1 <= wr_en when select_write_reg = "001" else '0';
    wr_en_2 <= wr_en when select_write_reg = "010" else '0';
    wr_en_3 <= wr_en when select_write_reg = "011" else '0';
    wr_en_4 <= wr_en when select_write_reg = "100" else '0';
    wr_en_5 <= wr_en when select_write_reg = "101" else '0';
    wr_en_6 <= wr_en when select_write_reg = "110" else '0';
    wr_en_7 <= wr_en when select_write_reg = "111" else '0';
  
    reg_a <= data_out_reg_1 when select_reg_a = "001" else 
      data_out_reg_2 when select_reg_a = "010" else 
      data_out_reg_3 when select_reg_a = "011" else 
      data_out_reg_4 when select_reg_a = "100" else 
      data_out_reg_5 when select_reg_a = "101" else 
      data_out_reg_6 when select_reg_a = "110" else 
      data_out_reg_7 when select_reg_a = "111" else 
      "00000000000000";
  
    reg_b <= data_out_reg_1 when select_reg_b = "001" else 
      data_out_reg_2 when select_reg_b = "010" else 
      data_out_reg_3 when select_reg_b = "011" else 
      data_out_reg_4 when select_reg_b = "100" else 
      data_out_reg_5 when select_reg_b = "101" else 
      data_out_reg_6 when select_reg_b = "110" else 
      data_out_reg_7 when select_reg_b = "111" else 
      "00000000000000";
end architecture;

alu.vhd
library ieee;
use ieee.std_logic_1164.all;
use ieee.numeric_std.all;

entity alu is
    port(
        x, y: in unsigned(13 downto 0);
        select_op: in unsigned(2 downto 0);
        output: out unsigned(13 downto 0);
        carry : out std_logic;
        zero : out std_logic
    );
    signal is_odd: unsigned(13 downto 0);
end entity;

architecture a_alu of alu is
begin
    is_odd <=
    "00000000000001" when x(0) = '1' else
    "00000000000000" when x(0) = '0' else
    "00000000000000";
    
    output <=
    x+y when select_op="000" else
    x-y when select_op="001" else
    x AND y when select_op="010" else
    x XOR y when select_op="011" else
    NOT x when select_op="100" else
    x OR y when select_op="101" else
    is_odd when select_op="110" else
    "00000000000000";

    zero <= '1' when x-y = "00000000000000" else '0';
    
    carry <= '1' when y > x else '0';
    
end architecture;

-- subtração

state_machine.vhd
library ieee;
use ieee.std_logic_1164.all;
use ieee.numeric_std.all;

entity state_machine is
    port(
        clk : in std_logic;
        rst : in std_logic;
        state : out unsigned(1 downto 0)
    );
end entity;

architecture a_state_machine of state_machine is
    signal internal_state: unsigned(1 downto 0);
begin
    process(clk,rst)
    begin
        if rst='1' then
            internal_state <= "00";
        elsif rising_edge(clk) then
            if (internal_state = "10") then
                internal_state <= "0";
            else
                internal_state <= internal_state + 1;
            end if;
        end if;
    end process;

    state <= internal_state;
end architecture;

uc.vhd
library ieee;
use ieee.std_logic_1164.all;
use ieee.numeric_std.all;

entity uc is
    port(
        clk : IN  std_logic;
        rst : IN  std_logic;
        instruction_in : IN unsigned (13 downto 0);
        instruction_out : OUT unsigned (13 downto 0);
        PC: OUT unsigned(13 downto 0);
        fetch: OUT std_logic; -- booleano para dizer se esta em fetch
        decode: OUT std_logic; -- booleano para dizer se esta em decode
        execute: OUT std_logic; -- booleano para dizer se esta em execute
        state: OUT unsigned(1 downto 0) -- booleano para dizer em que etapa esta a maquina de estados
    );
end entity uc;

architecture a_uc of uc is
    component reg14bits is
        port
        (
            clk      : IN std_logic ;
            rst      : IN std_logic ;
            wr_en    : IN std_logic ;
            data_in  : IN unsigned (13 downto 0);
            data_out : OUT unsigned (13 downto 0)
        );
    end component;

    component state_machine is
        port
        (
            clk : in std_logic;
            rst : in std_logic;
            state : out unsigned(1 downto 0)
        );
    end component state_machine;
    
    signal PC_reg_in, PC_reg_out : unsigned(13 downto 0); -- input e output do program counter
    signal opcode : unsigned(3 downto 0); -- opcode -> add, jump, nop, etc
    signal PC_reg_wr_en, instruction_reg_wr_en, jump_en : std_logic; -- enables = permite escrever nos registradores ou fazer jump
    -- middlware signal para saidas
    signal instruction_out_internal : unsigned(13 downto 0); -- estado da maquina de estados
    signal state_internal : unsigned(1 downto 0); -- estado da maquina de estados
    signal fetch_internal, decode_internal, execute_internal : std_logic; -- booleano para dizer em que etapa esta a maquina de estados
    
begin
    PC_reg: reg14bits
    port map
    (
        clk      => clk,
        rst      => rst,
        wr_en    => PC_reg_wr_en,
        data_in  => PC_reg_in,
        data_out => PC_reg_out
    );

    instruction_reg: reg14bits
    port map
    (
        clk      => clk,
        rst      => rst,
        wr_en    => instruction_reg_wr_en,
        data_in  => instruction_in,
        data_out => instruction_out_internal
    );
    
    state_machine1: state_machine
    port map
    (
        clk   => clk,
        rst   => rst,
        state => state_internal
    );

    -- estados da maquina de estados
    fetch_internal <= '1' when state_internal = "00" else '0'; -- se está em fetch precisa escrever no instruction register
    instruction_reg_wr_en <= fetch_internal;
    decode_internal <= '1' when state_internal = "01" else '0'; -- se está em decode precisa escrever no program counter
    PC_reg_wr_en <= decode_internal;
    execute <= '1' when state_internal = "10" else '0'; -- se está em execute ou nao

    -- dados da instrucao
    opcode <= instruction_out_internal(13 downto 10); -- opcode sao os 4 bits mais significativos da instrucao

    -- TODO: fiquei na duvida se pegava o jump pela ROM fazendo (13 downto 10), existe variavel global entre arquivos? arquivo de constantes talvez para graver opcodes
    jump_en <= '1' when opcode = "1111" else '0';

    -- se for jump, concatenar MSB do PC com o LSB da instrucao
    -- se nao somar 1
    PC_reg_in <= PC_reg_out(13 downto 10) & instruction_out_internal (9 downto 0) when jump_en = '1' else
    PC_reg_out + 1;--"0000000000001";

    -- repassando para output
    PC <= PC_reg_out;
    instruction_out <= instruction_out_internal;
    state <= state_internal;
    fetch <= fetch_internal;
    decode <= decode_internal;
    execute <= execute_internal;
end architecture a_uc;

rom.vhd
library IEEE;
use IEEE.std_logic_1164.all;
use IEEE.numeric_std.all;

entity rom is
    port(
        clk: IN STD_LOGIC;
        address: IN unsigned(9 downto 0);
        data: OUT unsigned(13 downto 0)
    );
end entity rom;

architecture a_rom of rom is
    type mem is array (0 to 127) of unsigned(13 downto 0);
    constant rom_content : mem := (
        0 => B"0001_1_011_000000", -- ADD R3 0
        1 => B"0001_1_100_000000", -- ADD R4 0
        2 => B"0011_010_011_0000", -- MOV R2 <- R3 (salvar o valor de R3)
        3 => B"0001_0_011_100_000", -- ADD R3 R4
        4 => B"0011_100_011_0000", -- MOV R4 <- R3
        5 => B"0011_011_010_0000", -- MOV R3 <- R2 (retornar o valor de R3)
        6 => B"0001_1_011_000001", -- ADD R3 1
        7 => B"0011_010_011_0000", -- MOV R2 <- R3 (salvar o valor de R3)
        8 => B"0010_1_011_011110", -- SUB R3 30
        9 => B"0011_011_010_0000", -- MOV R3 <- R2 (retornar o valor de R3)
        10 => B"1110_01_00001000", -- JMPR < 8
        11 => B"0011_101_100_0000", -- MOV R5 <- R4
        others => (others => '0')
    );
begin
    process(clk)
    begin
        if(rising_edge(clk)) then
            data <= rom_content(to_integer(address));
        end if;
    end process;
end architecture;

processor.vhd
library IEEE;
use IEEE.std_logic_1164.all;
use IEEE.numeric_std.all;

entity processor is
    port (
        clk       : in  std_logic;
        rst       : in  std_logic;
        state    : out unsigned(1 downto 0);
        PC        : out unsigned(13 downto 0);
        instruction : out unsigned(13 downto 0);
        reg_a_output      : out unsigned(13 downto 0);
        reg_b_output      : out unsigned(13 downto 0);
        output     : out unsigned(13 downto 0)
    );
end entity processor;

architecture a_processor of processor is
    component rom is
        port
        (
            clk     : IN STD_LOGIC ;
            address : IN unsigned (9 downto 0);
            data    : OUT unsigned (13 downto 0)
        );
    end component;
    
    component uc is
        port
        (
            clk             : IN std_logic ;
            rst             : IN std_logic ;
            instruction_in  : IN unsigned (13 downto 0);
            instruction_out : OUT unsigned (13 downto 0);
            PC              : OUT unsigned (13 downto 0);
            fetch           : OUT std_logic ;
            decode          : OUT std_logic ;
            execute         : OUT std_logic ;
            state           : OUT unsigned (1 downto 0)
        );
    end component;

    component alu is
        port
        (
            x         : IN unsigned (13 downto 0);
            y         : IN unsigned (13 downto 0);
            select_op : IN unsigned (2 downto 0);
            output    : OUT unsigned (13 downto 0);
            carry     : OUT std_logic;
            zero      : OUT std_logic
        );
    end component;

    component reg_bank is
        port
        (
            clk              : IN std_logic ;
            rst              : IN std_logic ;
            wr_en            : IN std_logic ;
            select_reg_a     : IN unsigned (2 downto 0);
            select_reg_b     : IN unsigned (2 downto 0);
            select_write_reg : IN unsigned (2 downto 0);
            write_data       : IN unsigned (13 downto 0);
            reg_a            : OUT unsigned (13 downto 0);
            reg_b            : OUT unsigned (13 downto 0)
        );
    end component;

    signal zero, carry : std_logic; -- flag real -> somente atualizada em operacoes de ula (add, sub)
    signal zero_internal, carry_internal : std_logic; -- saida da ula indicando carry e zero
    signal alu_x, alu_y, alu_out, proc_regA, proc_regB : unsigned(13 downto 0); -- portas da ula

    signal reg_bank_wr_en, sel_in_alu : std_logic; -- enable para saber se vai escrever no banco, seletor de operacao da ula
    signal sel_write_reg, sel_reg_a, sel_reg_b, select_op : unsigned(2 downto 0);

    signal instruction_address : unsigned(9 downto 0); -- ROM input
    signal PC_internal : unsigned(13 downto 0); -- Resultado do PC
    signal rom_output : unsigned(13 downto 0); -- endereco da ROM

    signal state_internal : unsigned(1 downto 0); -- estado da maquina de estados
    signal fetch, execute, decode : std_logic; -- booleano que indica qual estado esta a maquina de estados

    signal instruction_reg : unsigned(13 downto 0); -- registrador que guarda a intrucao usada
    signal opcode : unsigned(13 downto 10);

    signal select_add_sub_source : std_logic; -- flag que indica se a operacao usa registrador ou constante
    signal select_compare : unsigned(1 downto 0); -- 2 bits para indicar qual a comparacao
    signal top_level : unsigned(13 downto 0);


    constant opcode_nop : unsigned(3 downto 0) := "0000";
    constant opcode_add : unsigned(3 downto 0) := "0001";
    constant opcode_sub : unsigned(3 downto 0) := "0010";
    constant opcode_move : unsigned(3 downto 0) := "0011";
    constant opcode_jump : unsigned(3 downto 0) := "1111";
    constant opcode_jump_rel : unsigned(3 downto 0) := "1110";

begin
    rom1: rom
    port map (
        clk => clk,
        address => instruction_address,
        data => rom_output
    );
    
    uc1: UC
    port map (
        clk => clk,
        rst => rst,
        instruction_in => rom_output,
        instruction_out => instruction_reg,
        state => state_internal,
        fetch => fetch,
        decode => decode,
        execute => execute,
        PC => PC_internal
    );
    
    alu1 : alu
    port map
    (
        x => alu_x,
        y => alu_y,
        select_op => select_op,
        output => alu_out,
        carry => carry_internal,
        zero => zero_internal
    );
    
    regs: reg_bank
    port map(
        clk => clk,
        rst => rst,
        wr_en => reg_bank_wr_en,
        select_write_reg => sel_write_reg, -- operacoes sempre escritas no reg a
        select_reg_a => sel_write_reg, -- operacoes sempre no reg a
        select_reg_b => sel_reg_b,
        write_data => alu_out,
        reg_a => proc_regA,
        reg_b => proc_regB
    );
    
    opcode <= instruction_reg(13 downto 10); -- opcode sao os 4 bits mais significativos da instrucao (MSB)

    select_add_sub_source <= instruction_reg(9); -- select do add e sub, para saber se ira pegar de um registrador ou constante (add ou addi)
    select_compare <= instruction_reg(9 downto 8); -- select de comparacao, maior, etc
    
    top_level <= "00000000" & instruction_reg(5 downto 0) when opcode = opcode_add or opcode = opcode_sub else -- Resto do add é a constante da operação executada
                "000000" & instruction_reg(7 downto 0) when opcode = opcode_jump_rel else -- Delta do branch
                "00000000000000";
    
    -- procurando qual o registrador b sera usado para a operacao
    sel_reg_b <= instruction_reg(6 downto 4) when opcode = opcode_move else
    instruction_reg(5 downto 3) when ((opcode = opcode_add or opcode = opcode_sub) and select_add_sub_source = '0') else
                 "000";

    reg_bank_wr_en <= '1' when execute = '1' and (opcode = opcode_add or opcode = opcode_sub or opcode = opcode_move) else '0';

    sel_in_alu <= '0' when (((opcode = opcode_add or opcode = opcode_sub) and select_add_sub_source = '0') or opcode = opcode_move) else '1';

    sel_write_reg <= instruction_reg(8 downto 6) when (opcode = opcode_add or opcode = opcode_sub) else
    instruction_reg(9 downto 7) when (opcode = opcode_move) else
                     "000"; -- Sempre escreve no regA - no caso ira cair nessa condicao para jmps, jmpr e nop, ou seja, write enable estara em 0
    
    select_op <= "000" when opcode = opcode_add or opcode = opcode_move else
                 "001" when opcode = opcode_sub else
                 "111"; -- operacao de jump, nop e jmpr faz nada na ula

    -- atualizar flags em operacao de ula -> fixado em sub, poderia ser no add tambem?
    zero <= zero_internal when opcode = opcode_sub;
    carry <= carry_internal when opcode = opcode_sub;

    instruction_address <= PC_internal(9 downto 0) - top_level(9 downto 0) when opcode = opcode_jump_rel and zero = select_compare(1) and carry = select_compare(0)
else PC_internal(9 downto 0);

    -- se for move pegar o registrador 0 para fazer 0 + registrador
    alu_x <= "00000000000000" when opcode = opcode_move else proc_regA;
    alu_y <= proc_regB  when sel_in_alu = '0' else
    top_level  when sel_in_alu = '1' else
             "00000000000000";

    state <= state_internal;
    PC <= PC_internal;
    output <= alu_out;
    instruction <= instruction_reg;
    reg_a_output <= proc_regA;
    reg_b_output <= proc_regB;
end architecture a_processor;

-- Operação de ula escreve nas flags de carry e zero
-- Agt faz uma operação de jump condicional depois de um sub e olha as flags
-- só atualiza flag se for conta de ula, ignorar jump etc

processor_tb.vhd
library ieee;
use ieee.std_logic_1164.all;
use ieee.numeric_std.all;

entity processor_tb is
end;

architecture a_processor_tb of processor_tb is
    component processor is
        port
        (
            clk          : IN std_logic ;
            rst          : IN std_logic ;
            state        : OUT unsigned (1 downto 0);
            PC           : OUT unsigned (13 downto 0);
            instruction  : OUT unsigned (13 downto 0);
            reg_a_output : OUT unsigned (13 downto 0);
            reg_b_output : OUT unsigned (13 downto 0);
            output       : OUT unsigned (13 downto 0)
        );
    end component;
    
    constant period_time : time := 100 ns;
    signal finished : std_logic := '0';
    
    signal clk, rst: std_logic;
    signal output, PC, instruction, reg_a_output, reg_b_output : unsigned(13 downto 0);
    signal state : unsigned(1 downto 0); -- estado da maquina de estados
    
begin
    uut: processor
    port map
    (
        clk          => clk,
        rst          => rst,
        state        => state,
        PC           => PC,
        instruction  => instruction,
        reg_a_output => reg_a_output,
        reg_b_output => reg_b_output,
        output       => output
    );

    reset_global: process
    begin
        rst <= '1';
        wait for period_time*2;
        rst <= '0';
        wait;
    end process reset_global;
    
    sim_time_proc: process
    begin
        wait for 500 us;
        finished <= '1';
        wait;
    end process sim_time_proc;
    
    clk_proc: process
    begin
        while finished /= '1' loop
            clk <= '0';
            wait for period_time / 2;
            clk <= '1';
            wait for period_time / 2;
        end loop;
        wait;
    end process clk_proc;

end architecture a_processor_tb;

processor_tb.vcd
$date
  Sat May 28 16:39:17 2022
$end
$version
  GHDL v0
$end
$timescale
  1 fs
$end
$scope module standard $end
$upscope $end
$scope module std_logic_1164 $end
$upscope $end
$scope module numeric_std $end
$upscope $end
$scope module processor_tb $end
$var reg 1 ! finished $end
$var reg 1 " clk $end
$var reg 1 # rst $end
$var reg 14 $ output[13:0] $end
$var reg 14 % pc[13:0] $end
$var reg 14 & instruction[13:0] $end
$var reg 14 ' reg_a_output[13:0] $end
$var reg 14 ( reg_b_output[13:0] $end
$var reg 2 ) state[1:0] $end
$scope module uut $end
$var reg 1 * clk $end
$var reg 1 + rst $end
$var reg 2 , state[1:0] $end
$var reg 14 - pc[13:0] $end
$var reg 14 . instruction[13:0] $end
$var reg 14 / reg_a_output[13:0] $end
$var reg 14 0 reg_b_output[13:0] $end
$var reg 14 1 output[13:0] $end
$var reg 1 2 zero $end
$var reg 1 3 carry $end
$var reg 1 4 zero_internal $end
$var reg 1 5 carry_internal $end
$var reg 14 6 alu_x[13:0] $end
$var reg 14 7 alu_y[13:0] $end
$var reg 14 8 alu_out[13:0] $end
$var reg 14 9 proc_rega[13:0] $end
$var reg 14 : proc_regb[13:0] $end
$var reg 1 ; reg_bank_wr_en $end
$var reg 1 < sel_in_alu $end
$var reg 3 = sel_write_reg[2:0] $end
$var reg 3 > sel_reg_a[2:0] $end
$var reg 3 ? sel_reg_b[2:0] $end
$var reg 3 @ select_op[2:0] $end
$var reg 10 A instruction_address[9:0] $end
$var reg 14 B pc_internal[13:0] $end
$var reg 14 C rom_output[13:0] $end
$var reg 2 D state_internal[1:0] $end
$var reg 1 E fetch $end
$var reg 1 F execute $end
$var reg 1 G decode $end
$var reg 14 H instruction_reg[13:0] $end
$var reg 4 I opcode[13:10] $end
$var reg 1 J select_add_sub_source $end
$var reg 2 K select_compare[1:0] $end
$var reg 14 L top_level[13:0] $end
$scope module rom1 $end
$var reg 1 M clk $end
$var reg 10 N address[9:0] $end
$var reg 14 O data[13:0] $end
$upscope $end
$scope module uc1 $end
$var reg 1 P clk $end
$var reg 1 Q rst $end
$var reg 14 R instruction_in[13:0] $end
$var reg 14 S instruction_out[13:0] $end
$var reg 14 T pc[13:0] $end
$var reg 1 U fetch $end
$var reg 1 V decode $end
$var reg 1 W execute $end
$var reg 2 X state[1:0] $end
$var reg 14 Y pc_reg_in[13:0] $end
$var reg 14 Z pc_reg_out[13:0] $end
$var reg 4 [ opcode[3:0] $end
$var reg 1 \ pc_reg_wr_en $end
$var reg 1 ] instruction_reg_wr_en $end
$var reg 1 ^ jump_en $end
$var reg 14 _ instruction_out_internal[13:0] $end
$var reg 2 ` state_internal[1:0] $end
$var reg 1 a fetch_internal $end
$var reg 1 b decode_internal $end
$var reg 1 c execute_internal $end
$scope module pc_reg $end
$var reg 1 d clk $end
$var reg 1 e rst $end
$var reg 1 f wr_en $end
$var reg 14 g data_in[13:0] $end
$var reg 14 h data_out[13:0] $end
$var reg 14 i reg[13:0] $end
$upscope $end
$scope module instruction_reg $end
$var reg 1 j clk $end
$var reg 1 k rst $end
$var reg 1 l wr_en $end
$var reg 14 m data_in[13:0] $end
$var reg 14 n data_out[13:0] $end
$var reg 14 o reg[13:0] $end
$upscope $end
$scope module state_machine1 $end
$var reg 1 p clk $end
$var reg 1 q rst $end
$var reg 2 r state[1:0] $end
$var reg 2 s internal_state[1:0] $end
$upscope $end
$upscope $end
$scope module alu1 $end
$var reg 14 t x[13:0] $end
$var reg 14 u y[13:0] $end
$var reg 3 v select_op[2:0] $end
$var reg 14 w output[13:0] $end
$var reg 1 x carry $end
$var reg 1 y zero $end
$var reg 14 z is_odd[13:0] $end
$upscope $end
$scope module regs $end
$var reg 1 { clk $end
$var reg 1 | rst $end
$var reg 1 } wr_en $end
$var reg 3 !" select_reg_a[2:0] $end
$var reg 3 "" select_reg_b[2:0] $end
$var reg 3 #" select_write_reg[2:0] $end
$var reg 14 $" write_data[13:0] $end
$var reg 14 %" reg_a[13:0] $end
$var reg 14 &" reg_b[13:0] $end
$var reg 1 '" wr_en_1 $end
$var reg 1 (" wr_en_2 $end
$var reg 1 )" wr_en_3 $end
$var reg 1 *" wr_en_4 $end
$var reg 1 +" wr_en_5 $end
$var reg 1 ," wr_en_6 $end
$var reg 1 -" wr_en_7 $end
$var reg 14 ." data_out_reg_1[13:0] $end
$var reg 14 /" data_out_reg_2[13:0] $end
$var reg 14 0" data_out_reg_3[13:0] $end
$var reg 14 1" data_out_reg_4[13:0] $end
$var reg 14 2" data_out_reg_5[13:0] $end
$var reg 14 3" data_out_reg_6[13:0] $end
$var reg 14 4" data_out_reg_7[13:0] $end
$scope module reg1 $end
$var reg 1 5" clk $end
$var reg 1 6" rst $end
$var reg 1 7" wr_en $end
$var reg 14 8" data_in[13:0] $end
$var reg 14 9" data_out[13:0] $end
$var reg 14 :" reg[13:0] $end
$upscope $end
$scope module reg2 $end
$var reg 1 ;" clk $end
$var reg 1 <" rst $end
$var reg 1 =" wr_en $end
$var reg 14 >" data_in[13:0] $end
$var reg 14 ?" data_out[13:0] $end
$var reg 14 @" reg[13:0] $end
$upscope $end
$scope module reg3 $end
$var reg 1 A" clk $end
$var reg 1 B" rst $end
$var reg 1 C" wr_en $end
$var reg 14 D" data_in[13:0] $end
$var reg 14 E" data_out[13:0] $end
$var reg 14 F" reg[13:0] $end
$upscope $end
$scope module reg4 $end
$var reg 1 G" clk $end
$var reg 1 H" rst $end
$var reg 1 I" wr_en $end
$var reg 14 J" data_in[13:0] $end
$var reg 14 K" data_out[13:0] $end
$var reg 14 L" reg[13:0] $end
$upscope $end
$scope module reg5 $end
$var reg 1 M" clk $end
$var reg 1 N" rst $end
$var reg 1 O" wr_en $end
$var reg 14 P" data_in[13:0] $end
$var reg 14 Q" data_out[13:0] $end
$var reg 14 R" reg[13:0] $end
$upscope $end
$scope module reg6 $end
$var reg 1 S" clk $end
$var reg 1 T" rst $end
$var reg 1 U" wr_en $end
$var reg 14 V" data_in[13:0] $end
$var reg 14 W" data_out[13:0] $end
$var reg 14 X" reg[13:0] $end
$upscope $end
$scope module reg7 $end
$var reg 1 Y" clk $end
$var reg 1 Z" rst $end
$var reg 1 [" wr_en $end
$var reg 14 \" data_in[13:0] $end
$var reg 14 ]" data_out[13:0] $end
$var reg 14 ^" reg[13:0] $end
$upscope $end
$upscope $end
$upscope $end
$upscope $end
$enddefinitions $end
#0
0!
0"
1#
b00000000000000 $
b00000000000000 %
b00000000000000 &
b00000000000000 '
b00000000000000 (
b00 )
0*
1+
b00 ,
b00000000000000 -
b00000000000000 .
b00000000000000 /
b00000000000000 0
b00000000000000 1
U2
U3
14
05
b00000000000000 6
b00000000000000 7
b00000000000000 8
b00000000000000 9
b00000000000000 :
0;
1<
b000 =
bUUU >
b000 ?
b111 @
b0000000000 A
b00000000000000 B
bUUUUUUUUUUUUUU C
b00 D
1E
0F
0G
b00000000000000 H
b0000 I
0J
b00 K
b00000000000000 L
0M
b0000000000 N
bUUUUUUUUUUUUUU O
0P
1Q
bUUUUUUUUUUUUUU R
b00000000000000 S
b00000000000000 T
1U
0V
0W
b00 X
b00000000000001 Y
b00000000000000 Z
b0000 [
0\
1]
0^
b00000000000000 _
b00 `
1a
0b
0c
0d
1e
0f
b00000000000001 g
b00000000000000 h
b00000000000000 i
0j
1k
1l
bUUUUUUUUUUUUUU m
b00000000000000 n
b00000000000000 o
0p
1q
b00 r
b00 s
b00000000000000 t
b00000000000000 u
b111 v
b00000000000000 w
0x
1y
b00000000000000 z
0{
1|
0}
b000 !"
b000 ""
b000 #"
b00000000000000 $"
b00000000000000 %"
b00000000000000 &"
0'"
0("
0)"
0*"
0+"
0,"
0-"
b00000000000000 ."
b00000000000000 /"
b00000000000000 0"
b00000000000000 1"
b00000000000000 2"
b00000000000000 3"
b00000000000000 4"
05"
16"
07"
b00000000000000 8"
b00000000000000 9"
b00000000000000 :"
0;"
1<"
0="
b00000000000000 >"
b00000000000000 ?"
b00000000000000 @"
0A"
1B"
0C"
b00000000000000 D"
b00000000000000 E"
b00000000000000 F"
0G"
1H"
0I"
b00000000000000 J"
b00000000000000 K"
b00000000000000 L"
0M"
1N"
0O"
b00000000000000 P"
b00000000000000 Q"
b00000000000000 R"
0S"
1T"
0U"
b00000000000000 V"
b00000000000000 W"
b00000000000000 X"
0Y"
1Z"
0["
b00000000000000 \"
b00000000000000 ]"
b00000000000000 ^"
#50000000
1"
1*
b00011011000000 C
1M
b00011011000000 O
1P
b00011011000000 R
1d
1j
b00011011000000 m
1p
1{
15"
1;"
1A"
1G"
1M"
1S"
1Y"
#100000000
0"
0*
0M
0P
0d
0j
0p
0{
05"
0;"
0A"
0G"
0M"
0S"
0Y"
#150000000
1"
1*
1M
1P
1d
1j
1p
1{
15"
1;"
1A"
1G"
1M"
1S"
1Y"
#200000000
0"
0#
0*
0+
0M
0P
0Q
0d
0e
0j
0k
0p
0q
0{
0|
05"
06"
0;"
0<"
0A"
0B"
0G"
0H"
0M"
0N"
0S"
0T"
0Y"
0Z"
#250000000
1"
b00011011000000 &
b01 )
1*
b01 ,
b00011011000000 .
b011 =
b000 @
b01 D
0E
1G
b00011011000000 H
b0001 I
1J
b10 K
1M
1P
b00011011000000 S
0U
1V
b01 X
b0001 [
1\
0]
b00011011000000 _
b01 `
0a
1b
1d
1f
1j
0l
b00011011000000 n
b00011011000000 o
1p
b01 r
b01 s
b000 v
1{
b011 !"
b011 #"
15"
1;"
1A"
1G"
1M"
1S"
1Y"
#300000000
0"
0*
0M
0P
0d
0j
0p
0{
05"
0;"
0A"
0G"
0M"
0S"
0Y"
#350000000
1"
b00000000000001 %
b10 )
1*
b10 ,
b00000000000001 -
1;
b0000000001 A
b00000000000001 B
b10 D
1F
0G
1M
b0000000001 N
1P
b00000000000001 T
0V
1W
b10 X
b00000000000010 Y
b00000000000001 Z
0\
b10 `
0b
1c
1d
0f
b00000000000010 g
b00000000000001 h
b00000000000001 i
1j
1p
b10 r
b10 s
1{
1}
1)"
15"
1;"
1A"
1C"
1G"
1M"
1S"
1Y"
#400000000
0"
0*
0M
0P
0d
0j
0p
0{
05"
0;"
0A"
0G"
0M"
0S"
0Y"
#450000000
1"
b00 )
1*
b00 ,
0;
b00011100000000 C
b00 D
1E
0F
1M
b00011100000000 O
1P
b00011100000000 R
1U
0W
b00 X
1]
b00 `
1a
0c
1d
1j
1l
b00011100000000 m
1p
b00 r
b00 s
1{
0}
0)"
15"
1;"
1A"
0C"
1G"
1M"
1S"
1Y"
#500000000
0"
0*
0M
0P
0d
0j
0p
0{
05"
0;"
0A"
0G"
0M"
0S"
0Y"
#550000000
1"
b00011100000000 &
b01 )
1*
b01 ,
b00011100000000 .
b100 =
b01 D
0E
1G
b00011100000000 H
b11 K
1M
1P
b00011100000000 S
0U
1V
b01 X
1\
0]
b00011100000000 _
b01 `
0a
1b
1d
1f
1j
0l
b00011100000000 n
b00011100000000 o
1p
b01 r
b01 s
1{
b100 !"
b100 #"
15"
1;"
1A"
1G"
1M"
1S"
1Y"
#600000000
0"
0*
0M
0P
0d
0j
0p
0{
05"
0;"
0A"
0G"
0M"
0S"
0Y"
#650000000
1"
b00000000000010 %
b10 )
1*
b10 ,
b00000000000010 -
1;
b0000000010 A
b00000000000010 B
b10 D
1F
0G
1M
b0000000010 N
1P
b00000000000010 T
0V
1W
b10 X
b00000000000011 Y
b00000000000010 Z
0\
b10 `
0b
1c
1d
0f
b00000000000011 g
b00000000000010 h
b00000000000010 i
1j
1p
b10 r
b10 s
1{
1}
1*"
15"
1;"
1A"
1G"
1I"
1M"
1S"
1Y"
#700000000
0"
0*
0M
0P
0d
0j
0p
0{
05"
0;"
0A"
0G"
0M"
0S"
0Y"
#750000000
1"
b00 )
1*
b00 ,
0;
b00110100110000 C
b00 D
1E
0F
1M
b00110100110000 O
1P
b00110100110000 R
1U
0W
b00 X
1]
b00 `
1a
0c
1d
1j
1l
b00110100110000 m
1p
b00 r
b00 s
1{
0}
0*"
15"
1;"
1A"
1G"
0I"
1M"
1S"
1Y"
#800000000
0"
0*
0M
0P
0d
0j
0p
0{
05"
0;"
0A"
0G"
0M"
0S"
0Y"
#850000000
1"
b00000000000000 $
b00110100110000 &
b01 )
1*
b01 ,
b00110100110000 .
b00000000000000 1
14
05
b00000000000000 7
b00000000000000 8
0<
b010 =
b011 ?
b01 D
0E
1G
b00110100110000 H
b0011 I
0J
b01 K
b00000000000000 L
1M
1P
b00110100110000 S
0U
1V
b01 X
b0011 [
1\
0]
b00110100110000 _
b01 `
0a
1b
1d
1f
1j
0l
b00110100110000 n
b00110100110000 o
1p
b01 r
b01 s
b00000000000000 u
b00000000000000 w
0x
1y
1{
b010 !"
b011 ""
b010 #"
b00000000000000 $"
15"
b00000000000000 8"
1;"
b00000000000000 >"
1A"
b00000000000000 D"
1G"
b00000000000000 J"
1M"
b00000000000000 P"
1S"
b00000000000000 V"
1Y"
b00000000000000 \"
