reg16bits.vhd
library ieee;
use ieee.std_logic_1164.all;
use ieee.numeric_std.all;

entity reg16bits is
    port(
        clk : in std_logic;
        rst : in std_logic;
        wr_en : in std_logic;
        data_in : in unsigned(15 downto 0);
        data_out : out unsigned(15 downto 0)
    );
end entity;

architecture a_reg16bits of reg16bits is
    signal reg: unsigned(15 downto 0);
begin
    process(clk,rst,wr_en)
    begin
        if rst='1' then
            reg <= "0000000000000000";
        elsif wr_en='1' then
            if rising_edge(clk) then
                reg <= data_in;
            end if;
        end if;
    end process;

    data_out <= reg;
end architecture;

reg_bank.vhd
library ieee;
use ieee.std_logic_1164.all;
use ieee.numeric_std.all;

entity reg_bank is
    port(
        clk, rst, wr_en : in std_logic;
        select_reg_a, select_reg_b, select_write_reg : in unsigned(2 downto 0);
        write_data: in unsigned(15 downto 0);
        reg_a, reg_b : out unsigned(15 downto 0)
    );
end entity;

architecture a_reg_bank of reg_bank is
    component reg16bits is
        port
        (
            clk      : IN std_logic ;
            rst      : IN std_logic ;
            wr_en    : IN std_logic ;
            data_in  : IN unsigned (15 downto 0);
            data_out : OUT unsigned (15 downto 0)
        );
    end component;

    signal wr_en_1, wr_en_2, wr_en_3, wr_en_4, wr_en_5, wr_en_6, wr_en_7, wr_en_8 : std_logic;
    signal data_out_reg_1, data_out_reg_2, data_out_reg_3, data_out_reg_4, data_out_reg_5, data_out_reg_6, data_out_reg_7, data_out_reg_8: unsigned(15 downto 0);
begin
   reg1: reg16bits
    port map
    (
        clk      => clk,
        rst      => rst,
        wr_en    => wr_en_1,
        data_in  => write_data,
        data_out => data_out_reg_1
    );

    reg2: reg16bits
    port map
    (
        clk      => clk,
        rst      => rst,
        wr_en    => wr_en_2,
        data_in  => write_data,
        data_out => data_out_reg_2
    );

    reg3: reg16bits
    port map
    (
        clk      => clk,
        rst      => rst,
        wr_en    => wr_en_3,
        data_in  => write_data,
        data_out => data_out_reg_3
    );

    reg4: reg16bits
    port map
    (
        clk      => clk,
        rst      => rst,
        wr_en    => wr_en_4,
        data_in  => write_data,
        data_out => data_out_reg_4
    );

    reg5: reg16bits
    port map
    (
        clk      => clk,
        rst      => rst,
        wr_en    => wr_en_5,
        data_in  => write_data,
        data_out => data_out_reg_5
    );

    reg6: reg16bits
    port map
    (
        clk      => clk,
        rst      => rst,
        wr_en    => wr_en_6,
        data_in  => write_data,
        data_out => data_out_reg_6
    );

    reg7: reg16bits
    port map
    (
        clk      => clk,
        rst      => rst,
        wr_en    => wr_en_7,
        data_in  => write_data,
        data_out => data_out_reg_7
    );

   
    wr_en_1 <= wr_en when select_write_reg = "001" else '0';
    wr_en_2 <= wr_en when select_write_reg = "010" else '0';
    wr_en_3 <= wr_en when select_write_reg = "011" else '0';
    wr_en_4 <= wr_en when select_write_reg = "100" else '0';
    wr_en_5 <= wr_en when select_write_reg = "101" else '0';
    wr_en_6 <= wr_en when select_write_reg = "110" else '0';
    wr_en_7 <= wr_en when select_write_reg = "111" else '0';
  
    reg_a <= data_out_reg_1 when select_reg_a = "001" else 
      data_out_reg_2 when select_reg_a = "010" else 
      data_out_reg_3 when select_reg_a = "011" else 
      data_out_reg_4 when select_reg_a = "100" else 
      data_out_reg_5 when select_reg_a = "101" else 
      data_out_reg_6 when select_reg_a = "110" else 
      data_out_reg_7 when select_reg_a = "111" else 
      "0000000000000000";
  
    reg_b <= data_out_reg_1 when select_reg_b = "001" else 
      data_out_reg_2 when select_reg_b = "010" else 
      data_out_reg_3 when select_reg_b = "011" else 
      data_out_reg_4 when select_reg_b = "100" else 
      data_out_reg_5 when select_reg_b = "101" else 
      data_out_reg_6 when select_reg_b = "110" else 
      data_out_reg_7 when select_reg_b = "111" else 
      "0000000000000000";
end architecture;

reg_bank_tb.vhd
library ieee;
use ieee.std_logic_1164.all;
use ieee.numeric_std.all;

entity reg_bank_tb is
end;

architecture a_reg_bank_tb of reg_bank_tb is
    component reg_bank is
        port
        (
            clk              : IN std_logic ;
            rst              : IN std_logic ;
            wr_en            : IN std_logic ;
            select_reg_a     : IN unsigned (2 downto 0);
            select_reg_b     : IN unsigned (2 downto 0);
            select_write_reg : IN unsigned (2 downto 0);
            write_data       : IN unsigned (15 downto 0);
            reg_a            : OUT unsigned (15 downto 0);
            reg_b            : OUT unsigned (15 downto 0)
        );
    end component;
    constant period_time : time := 100 ns; -- tempo do clock
    signal finished : std_logic := '0'; -- booleano para indicar se o processo acabou

    signal clk, rst, wr_en : std_logic; -- clock, reset, write enable
    signal select_reg_a, select_reg_b, select_write_reg: unsigned(2 downto 0);
    signal write_data, reg_a, reg_b : unsigned(15 downto 0); -- input e output
begin
    uut: reg_bank
    port map
    (
        clk              => clk,
        rst              => rst,
        wr_en            => wr_en,
        select_reg_a     => select_reg_a,
        select_reg_b     => select_reg_b,
        select_write_reg => select_write_reg,
        write_data       => write_data,
        reg_a            => reg_a,
        reg_b            => reg_b
    );

    
    reset_global: process -- a cada duas vezes o período reseta o registro
    begin
        rst <= '1';
        wait for period_time*2;
        rst <= '0';
        wait;
    end process;
    
    sim_time_proc: process
    begin
        wait for 10 us; -- tempo de simulação
        finished <= '1';
        wait;
    end process sim_time_proc;
    
    clk_proc: process
    begin
        while finished /= '1' loop -- gera clock até que sim_time_proc termine
            clk <= '0';
            wait for period_time / 2;
            clk <= '1';
            wait for period_time / 2; -- subida
        end loop;
        wait;
    end process clk_proc;
    
    process -- sinais de teste
    begin
        wr_en <= '1';
        write_data <= "0000000000000010"; -- deve escrever 2 no registrador B (5)
        select_reg_a <= "010";
        select_reg_b <= "100";
        select_write_reg <= "100";
        wait for period_time*3;
        write_data <= "0000000000001000"; -- deve escrever 4 no registrador A (3)
        select_write_reg <= "010";
        wait for period_time*2;

        wr_en <= '0'; -- desativando o write enable
        write_data <= "0000000000000001"; -- dado que supostamente seria escrito no registrador A (3)
        select_reg_a <= "010";
        select_reg_b <= "100";
        select_write_reg <= "010";
        wait for period_time*2;

        wr_en <= '1'; -- ativando o write enable
        write_data <= "0000000000000001"; -- dado que supostamente seria escrito no registrador A (0), porém é o zero
        select_reg_a <= "000";
        select_reg_b <= "111";
        select_write_reg <= "000";
        wait for period_time*2;

        -- testando todos os registradores

        wr_en <= '1'; -- ativando o write enable
        select_reg_b <= "111";

        write_data <= "0000000000000001";
        select_reg_a <= "001";
        select_write_reg <= "001";
        wait for period_time*3;

        write_data <= "0000000000000010";
        select_reg_a <= "010";
        select_write_reg <= "010";
        wait for period_time*3;

        write_data <= "0000000000000100";
        select_reg_a <= "011";
        select_write_reg <= "011";
        wait for period_time*3;

        write_data <= "0000000000001000";
        select_reg_a <= "100";
        select_write_reg <= "100";
        wait for period_time*3;

        write_data <= "0000000000010000";
        select_reg_a <= "101";
        select_write_reg <= "101";
        wait for period_time*3;

        write_data <= "0000000000100000";
        select_reg_a <= "110";
        select_write_reg <= "110";
        wait for period_time*3;

        write_data <= "0000000001000000";
        select_reg_a <= "111";
        select_reg_b <= "000";
        select_write_reg <= "111";
        wait for period_time*3;
        wait;
    end process;
    
end architecture;

reg_bank_tb.vcd
$date
  Wed Apr 27 20:23:55 2022
$end
$version
  GHDL v0
$end
$timescale
  1 fs
$end
$scope module standard $end
$upscope $end
$scope module std_logic_1164 $end
$upscope $end
$scope module numeric_std $end
$upscope $end
$scope module reg_bank_tb $end
$var reg 1 ! finished $end
$var reg 1 " clk $end
$var reg 1 # rst $end
$var reg 1 $ wr_en $end
$var reg 3 % select_reg_a[2:0] $end
$var reg 3 & select_reg_b[2:0] $end
$var reg 3 ' select_write_reg[2:0] $end
$var reg 16 ( write_data[15:0] $end
$var reg 16 ) reg_a[15:0] $end
$var reg 16 * reg_b[15:0] $end
$scope module uut $end
$var reg 1 + clk $end
$var reg 1 , rst $end
$var reg 1 - wr_en $end
$var reg 3 . select_reg_a[2:0] $end
$var reg 3 / select_reg_b[2:0] $end
$var reg 3 0 select_write_reg[2:0] $end
$var reg 16 1 write_data[15:0] $end
$var reg 16 2 reg_a[15:0] $end
$var reg 16 3 reg_b[15:0] $end
$var reg 1 4 wr_en_1 $end
$var reg 1 5 wr_en_2 $end
$var reg 1 6 wr_en_3 $end
$var reg 1 7 wr_en_4 $end
$var reg 1 8 wr_en_5 $end
$var reg 1 9 wr_en_6 $end
$var reg 1 : wr_en_7 $end
$var reg 1 ; wr_en_8 $end
$var reg 16 < data_out_reg_1[15:0] $end
$var reg 16 = data_out_reg_2[15:0] $end
$var reg 16 > data_out_reg_3[15:0] $end
$var reg 16 ? data_out_reg_4[15:0] $end
$var reg 16 @ data_out_reg_5[15:0] $end
$var reg 16 A data_out_reg_6[15:0] $end
$var reg 16 B data_out_reg_7[15:0] $end
$var reg 16 C data_out_reg_8[15:0] $end
$scope module reg1 $end
$var reg 1 D clk $end
$var reg 1 E rst $end
$var reg 1 F wr_en $end
$var reg 16 G data_in[15:0] $end
$var reg 16 H data_out[15:0] $end
$var reg 16 I reg[15:0] $end
$upscope $end
$scope module reg2 $end
$var reg 1 J clk $end
$var reg 1 K rst $end
$var reg 1 L wr_en $end
$var reg 16 M data_in[15:0] $end
$var reg 16 N data_out[15:0] $end
$var reg 16 O reg[15:0] $end
$upscope $end
$scope module reg3 $end
$var reg 1 P clk $end
$var reg 1 Q rst $end
$var reg 1 R wr_en $end
$var reg 16 S data_in[15:0] $end
$var reg 16 T data_out[15:0] $end
$var reg 16 U reg[15:0] $end
$upscope $end
$scope module reg4 $end
$var reg 1 V clk $end
$var reg 1 W rst $end
$var reg 1 X wr_en $end
$var reg 16 Y data_in[15:0] $end
$var reg 16 Z data_out[15:0] $end
$var reg 16 [ reg[15:0] $end
$upscope $end
$scope module reg5 $end
$var reg 1 \ clk $end
$var reg 1 ] rst $end
$var reg 1 ^ wr_en $end
$var reg 16 _ data_in[15:0] $end
$var reg 16 ` data_out[15:0] $end
$var reg 16 a reg[15:0] $end
$upscope $end
$scope module reg6 $end
$var reg 1 b clk $end
$var reg 1 c rst $end
$var reg 1 d wr_en $end
$var reg 16 e data_in[15:0] $end
$var reg 16 f data_out[15:0] $end
$var reg 16 g reg[15:0] $end
$upscope $end
$scope module reg7 $end
$var reg 1 h clk $end
$var reg 1 i rst $end
$var reg 1 j wr_en $end
$var reg 16 k data_in[15:0] $end
$var reg 16 l data_out[15:0] $end
$var reg 16 m reg[15:0] $end
$upscope $end
$upscope $end
$upscope $end
$enddefinitions $end
#0
0!
0"
1#
1$
b010 %
b100 &
b100 '
b0000000000000010 (
b0000000000000000 )
b0000000000000000 *
0+
1,
1-
b010 .
b100 /
b100 0
b0000000000000010 1
b0000000000000000 2
b0000000000000000 3
04
05
06
17
08
09
0:
U;
b0000000000000000 <
b0000000000000000 =
b0000000000000000 >
b0000000000000000 ?
b0000000000000000 @
b0000000000000000 A
b0000000000000000 B
bUUUUUUUUUUUUUUUU C
0D
1E
0F
b0000000000000010 G
b0000000000000000 H
b0000000000000000 I
0J
1K
0L
b0000000000000010 M
b0000000000000000 N
b0000000000000000 O
0P
1Q
0R
b0000000000000010 S
b0000000000000000 T
b0000000000000000 U
0V
1W
1X
b0000000000000010 Y
b0000000000000000 Z
b0000000000000000 [
0\
1]
0^
b0000000000000010 _
b0000000000000000 `
b0000000000000000 a
0b
1c
0d
b0000000000000010 e
b0000000000000000 f
b0000000000000000 g
0h
1i
0j
b0000000000000010 k
b0000000000000000 l
b0000000000000000 m
#50000000
1"
1+
1D
1J
1P
1V
1\
1b
1h
#100000000
0"
0+
0D
0J
0P
0V
0\
0b
0h
#150000000
1"
1+
1D
1J
1P
1V
1\
1b
1h
#200000000
0"
0#
0+
0,
0D
0E
0J
0K
0P
0Q
0V
0W
0\
0]
0b
0c
0h
0i
#250000000
1"
b0000000000000010 *
1+
b0000000000000010 3
b0000000000000010 ?
1D
1J
1P
1V
b0000000000000010 Z
b0000000000000010 [
1\
1b
1h
#300000000
0"
b010 '
b0000000000001000 (
0+
b010 0
b0000000000001000 1
15
07
0D
b0000000000001000 G
0J
1L
b0000000000001000 M
0P
b0000000000001000 S
0V
0X
b0000000000001000 Y
0\
b0000000000001000 _
0b
b0000000000001000 e
0h
b0000000000001000 k
#350000000
1"
b0000000000001000 )
1+
b0000000000001000 2
b0000000000001000 =
1D
1J
b0000000000001000 N
b0000000000001000 O
1P
1V
1\
1b
1h
#400000000
0"
0+
0D
0J
0P
0V
0\
0b
0h
#450000000
1"
1+
1D
1J
1P
1V
1\
1b
1h
#500000000
0"
0$
b0000000000000001 (
0+
0-
b0000000000000001 1
05
0D
b0000000000000001 G
0J
0L
b0000000000000001 M
0P
b0000000000000001 S
0V
b0000000000000001 Y
0\
b0000000000000001 _
0b
b0000000000000001 e
0h
b0000000000000001 k
#550000000
1"
1+
1D
1J
1P
1V
1\
1b
1h
#600000000
0"
0+
0D
0J
0P
0V
0\
0b
0h
#650000000
1"
1+
1D
1J
1P
1V
1\
1b
1h
#700000000
0"
1$
b000 %
b111 &
b000 '
b0000000000000000 )
b0000000000000000 *
0+
1-
b000 .
b111 /
b000 0
b0000000000000000 2
b0000000000000000 3
0D
0J
0P
0V
0\
0b
0h
#750000000
1"
1+
1D
1J
1P
1V
1\
1b
1h
#800000000
0"
0+
0D
0J
0P
0V
0\
0b
0h
#850000000
1"
1+
1D
1J
1P
1V
1\
1b
1h
#900000000
0"
b001 %
b001 '
0+
b001 .
b001 0
14
0D
1F
0J
0P
0V
0\
0b
0h
#950000000
1"
b0000000000000001 )
1+
b0000000000000001 2
b0000000000000001 <
1D
b0000000000000001 H
b0000000000000001 I
1J
1P
1V
1\
1b
1h
#1000000000
0"
0+
0D
0J
0P
0V
0\
0b
0h
#1050000000
1"
1+
1D
1J
1P
1V
1\
1b
1h
#1100000000
0"
0+
0D
0J
0P
0V
0\
0b
0h
#1150000000
1"
1+
1D
1J
1P
1V
1\
1b
1h
#1200000000
0"
b010 %
b010 '
b0000000000000010 (
b0000000000001000 )
0+
b010 .
b010 0
b0000000000000010 1
b0000000000001000 2
04
15
0D
0F
b0000000000000010 G
0J
1L
b0000000000000010 M
0P
b0000000000000010 S
0V
b0000000000000010 Y
0\
b0000000000000010 _
0b
b0000000000000010 e
0h
b0000000000000010 k
#1250000000
1"
b0000000000000010 )
1+
b0000000000000010 2
b0000000000000010 =
1D
1J
b0000000000000010 N
b0000000000000010 O
1P
1V
1\
1b
1h
#1300000000
0"
0+
0D
0J
0P
0V
0\
0b
0h
#1350000000
1"
1+
1D
1J
1P
1V
1\
1b
1h
#1400000000
0"
0+
0D
0J
0P
0V
0\
0b
0h
#1450000000
1"
1+
1D
1J
1P
1V
1\
1b
1h
#1500000000
0"
b011 %
b011 '
b0000000000000100 (
b0000000000000000 )
0+
b011 .
b011 0
b0000000000000100 1
b0000000000000000 2
05
16
0D
b0000000000000100 G
0J
0L
b0000000000000100 M
0P
1R
b0000000000000100 S
0V
b0000000000000100 Y
0\
b0000000000000100 _
0b
b0000000000000100 e
0h
b0000000000000100 k
#1550000000
1"
b0000000000000100 )
1+
b0000000000000100 2
b0000000000000100 >
1D
1J
1P
b0000000000000100 T
b0000000000000100 U
1V
1\
1b
1h
#1600000000
0"
0+
0D
0J
0P
0V
0\
0b
0h
#1650000000
1"
1+
1D
1J
1P
1V
1\
1b
1h
#1700000000
0"
0+
0D
0J
0P
0V
0\
0b
0h
#1750000000
1"
1+
1D
1J
1P
1V
1\
1b
1h
#1800000000
0"
b100 %
b100 '
b0000000000001000 (
b0000000000000010 )
0+
b100 .
b100 0
b0000000000001000 1
b0000000000000010 2
06
17
0D
b0000000000001000 G
0J
b0000000000001000 M
0P
0R
b0000000000001000 S
0V
1X
b0000000000001000 Y
0\
b0000000000001000 _
0b
b0000000000001000 e
0h
b0000000000001000 k
#1850000000
1"
b0000000000001000 )
1+
b0000000000001000 2
b0000000000001000 ?
1D
1J
1P
1V
b0000000000001000 Z
b0000000000001000 [
1\
1b
1h
#1900000000
0"
0+
0D
0J
0P
0V
0\
0b
0h
#1950000000
1"
1+
1D
1J
1P
1V
1\
1b
1h
#2000000000
0"
0+
0D
0J
0P
0V
0\
0b
0h
#2050000000
1"
1+
1D
1J
1P
1V
1\
1b
1h
#2100000000
0"
b101 %
b101 '
b0000000000010000 (
b0000000000000000 )
0+
b101 .
b101 0
b0000000000010000 1
b0000000000000000 2
07
18
0D
b0000000000010000 G
0J
b0000000000010000 M
0P
b0000000000010000 S
0V
0X
b0000000000010000 Y
0\
1^
b0000000000010000 _
0b
b0000000000010000 e
0h
b0000000000010000 k
#2150000000
1"
b0000000000010000 )
1+
b0000000000010000 2
b0000000000010000 @
1D
1J
1P
1V
1\
b0000000000010000 `
b0000000000010000 a
1b
1h
#2200000000
0"
0+
0D
0J
0P
0V
0\
0b
0h
#2250000000
1"
1+
1D
1J
1P
1V
1\
1b
1h
#2300000000
0"
0+
0D
0J
0P
0V
0\
0b
0h
#2350000000
1"
1+
1D
1J
1P
1V
1\
1b
1h
#2400000000
0"
b110 %
b110 '
b0000000000100000 (
b0000000000000000 )
0+
b110 .
b110 0
b0000000000100000 1
b0000000000000000 2
08
19
0D
b0000000000100000 G
0J
b0000000000100000 M
0P
b0000000000100000 S
0V
b0000000000100000 Y
0\
0^
b0000000000100000 _
0b
1d
b0000000000100000 e
0h
b0000000000100000 k
#2450000000
1"
b0000000000100000 )
1+
b0000000000100000 2
b0000000000100000 A
1D
1J
1P
1V
1\
1b
b0000000000100000 f
b0000000000100000 g
1h
#2500000000
0"
0+
0D
0J
0P
0V
0\
0b
0h
#2550000000
1"
1+
1D
1J
1P
1V
1\
1b
1h
#2600000000
0"
0+
0D
0J
0P
0V
0\
0b
0h
#2650000000
1"
1+
1D
1J
1P
1V
1\
1b
1h
#2700000000
0"
b111 %
b000 &
b111 '
b0000000001000000 (
b0000000000000000 )
0+
b111 .
b000 /
b111 0
b0000000001000000 1
b0000000000000000 2
09
1:
0D
b0000000001000000 G
0J
b0000000001000000 M
0P
b0000000001000000 S
0V
b0000000001000000 Y
0\
b0000000001000000 _
0b
0d
b0000000001000000 e
0h
1j
b0000000001000000 k
#2750000000
1"
b0000000001000000 )
1+
b0000000001000000 2
b0000000001000000 B
1D
1J
1P
1V
1\
1b
1h
b0000000001000000 l
b0000000001000000 m
