rom.vhd
library IEEE;
use IEEE.std_logic_1164.all;
use IEEE.numeric_std.all;

entity rom is
    port(
        clk: IN STD_LOGIC;
        address: IN unsigned(6 downto 0);
        data: OUT unsigned(13 downto 0)
    );
end entity rom;

architecture a_rom of rom is
    type mem is array (0 to 127) of unsigned(13 downto 0);
    constant rom_content : mem := (
        0 => B"0000_0000000000", -- NOP
        1 => B"0001_0_001_011_000", -- ADD (Registrador) (Registrador)
        2 => B"0001_1_000_000000", -- ADD (Registrador) constante
        3 => B"0010_0_000_000_000", -- SUB (Registrador) (Registrador)
        4 => B"0010_1_000_000000", -- SUB (Registrador) constante
        5 => B"0011_001_011_0000", -- MOV (Registrador) (Registrador)
        6 => B"0000_0000000000", -- NOP
        7 => B"0000_0000000000", -- NOP
        8 => B"0000_0000000000", -- NOP
        9 => B"0000_0000000000", -- NOP
        10 => B"1111_0000000000", -- JA ADDR
        others => (others => '0')
    );
begin
    process(clk)
    begin
        if(rising_edge(clk)) then
            data <= rom_content(to_integer(address));
        end if;
    end process;
end architecture;

rom_tb.vhd
library ieee;
use ieee.std_logic_1164.all;
use ieee.numeric_std.all;

entity rom_tb is
end;

architecture a_rom_tb of rom_tb is
    component rom is
        port
        (
            clk     : IN STD_LOGIC ;
            address : IN unsigned (6 downto 0);
            data    : OUT unsigned (13 downto 0)
        );
    end component;
    
    constant period_time : time := 100 ns; -- tempo do clock
    signal finished : std_logic := '0'; -- booleano para indicar se o processo acabou
    signal clk : std_logic; -- clock, reset
    signal address: unsigned(6 downto 0); -- endereco
    signal data : unsigned(13 downto 0); -- output
begin
    uut: rom
    port map
    (
        clk     => clk,
        address => address,
        data    => data
    );
    
    sim_time_proc: process
    begin
        wait for 10 us; -- tempo de simulação
        finished <= '1';
        wait;
    end process sim_time_proc;
    
    clk_proc: process
    begin
        while finished /= '1' loop -- gera clock até que sim_time_proc termine
            clk <= '0';
            wait for period_time / 2;
            clk <= '1';
            wait for period_time / 2; -- subida
        end loop;
        wait;
    end process clk_proc;
    
    process -- sinais de teste
    begin
        address <= "0000000";
        wait for 100 ns;
        address <= "0000001";
        wait for 100 ns;
        address <= "0000010";
        wait for 100 ns;
        address <= "0000011";
        wait for 100 ns;
        address <= "0000100";
        wait for 100 ns;
        address <= "0000101";
        wait for 100 ns;
        address <= "0000110";
        wait for 100 ns;
        address <= "0000111";
        wait for 100 ns;
        address <= "0001000";
        wait for 100 ns;
        address <= "0001001";
        wait for 100 ns;
        address <= "0001010";
        wait for 100 ns;
        wait;
    end process;
    
end architecture;

rom_tb.vcd
$date
  Wed May 18 20:16:44 2022
$end
$version
  GHDL v0
$end
$timescale
  1 fs
$end
$scope module standard $end
$upscope $end
$scope module std_logic_1164 $end
$upscope $end
$scope module numeric_std $end
$upscope $end
$scope module rom_tb $end
$var reg 1 ! finished $end
$var reg 1 " clk $end
$var reg 7 # address[6:0] $end
$var reg 14 $ data[13:0] $end
$scope module uut $end
$var reg 1 % clk $end
$var reg 7 & address[6:0] $end
$var reg 14 ' data[13:0] $end
$upscope $end
$upscope $end
$enddefinitions $end
#0
0!
0"
b0000000 #
bUUUUUUUUUUUUUU $
0%
b0000000 &
bUUUUUUUUUUUUUU '
#50000000
1"
b00000000000000 $
1%
b00000000000000 '
#100000000
0"
b0000001 #
0%
b0000001 &
#150000000
1"
b00010001011000 $
1%
b00010001011000 '
#200000000
0"
b0000010 #
0%
b0000010 &
#250000000
1"
b00011000000000 $
1%
b00011000000000 '
#300000000
0"
b0000011 #
0%
b0000011 &
#350000000
1"
b00100000000000 $
1%
b00100000000000 '
#400000000
0"
b0000100 #
0%
b0000100 &
#450000000
1"
b00101000000000 $
1%
b00101000000000 '
#500000000
0"
b0000101 #
0%
b0000101 &
#550000000
1"
b00110010110000 $
1%
b00110010110000 '
#600000000
0"
b0000110 #
0%
b0000110 &
#650000000
1"
b00000000000000 $
1%
b00000000000000 '
#700000000
0"
b0000111 #
0%
b0000111 &
#750000000
1"
1%
#800000000
0"
b0001000 #
0%
b0001000 &
#850000000
1"
1%
#900000000
0"
b0001001 #
0%
b0001001 &
#950000000
1"
1%
#1000000000
0"
b0001010 #
0%
b0001010 &
#1050000000
1"
b11110000000000 $
1%
b11110000000000 '
