rom.vhd
library IEEE;
use IEEE.std_logic_1164.all;
use IEEE.numeric_std.all;

entity rom is
    port(
        clk: IN STD_LOGIC;
        address: IN unsigned(6 downto 0);
        data: OUT unsigned(13 downto 0)
    );
end entity rom;

architecture a_rom of rom is
    type mem is array (0 to 127) of unsigned(13 downto 0);
    constant rom_content : mem := (
        0 => "00000000000000",
        1 => "00000000000001",
        2 => "00000000000010",
        3 => "00000000000100",
        4 => "00000000001000",
        5 => "00000000010000",
        6 => "00000000100000",
        7 => "00000001000000",
        8 => "00000010000000",
        9 => "00000100000000",
        10 => "00000100000000",
        others => (others => '0')
    );
begin
    process(clk)
    begin
        if(rising_edge(clk)) then
            data <= rom_content(to_integer(address));
        end if;
    end process;
end architecture;

rom_tb.vhd
library ieee;
use ieee.std_logic_1164.all;
use ieee.numeric_std.all;

entity rom_tb is
end;

architecture a_rom_tb of rom_tb is
    component rom is
        port
        (
            clk     : IN STD_LOGIC ;
            address : IN unsigned (6 downto 0);
            data    : OUT unsigned (13 downto 0)
        );
    end component;
    
    constant period_time : time := 100 ns; -- tempo do clock
    signal finished : std_logic := '0'; -- booleano para indicar se o processo acabou
    signal clk : std_logic; -- clock, reset
    signal address: unsigned(6 downto 0); -- endereco
    signal data : unsigned(13 downto 0); -- output
begin
    uut: rom
    port map
    (
        clk     => clk,
        address => address,
        data    => data
    );
    
    sim_time_proc: process
    begin
        wait for 10 us; -- tempo de simulação
        finished <= '1';
        wait;
    end process sim_time_proc;
    
    clk_proc: process
    begin
        while finished /= '1' loop -- gera clock até que sim_time_proc termine
            clk <= '0';
            wait for period_time / 2;
            clk <= '1';
            wait for period_time / 2; -- subida
        end loop;
        wait;
    end process clk_proc;
    
    process -- sinais de teste
    begin
        address <= "0000000";
        wait for 100 ns;
        address <= "0000001";
        wait for 100 ns;
        address <= "0000010";
        wait for 100 ns;
        address <= "0000011";
        wait for 100 ns;
        address <= "0000100";
        wait for 100 ns;
        address <= "0000101";
        wait for 100 ns;
        address <= "0000110";
        wait for 100 ns;
        address <= "0000111";
        wait for 100 ns;
        address <= "0001000";
        wait for 100 ns;
        address <= "0001001";
        wait for 100 ns;
        address <= "0001010";
        wait for 100 ns;
        wait;
    end process;
    
end architecture;

rom_tb.vcd
$date
  Tue May  3 21:28:01 2022
$end
$version
  GHDL v0
$end
$timescale
  1 fs
$end
$scope module standard $end
$upscope $end
$scope module std_logic_1164 $end
$upscope $end
$scope module numeric_std $end
$upscope $end
$scope module rom_tb $end
$var reg 1 ! finished $end
$var reg 1 " clk $end
$var reg 7 # address[6:0] $end
$var reg 14 $ data[13:0] $end
$scope module uut $end
$var reg 1 % clk $end
$var reg 7 & address[6:0] $end
$var reg 14 ' data[13:0] $end
$upscope $end
$upscope $end
$enddefinitions $end
#0
0!
0"
b0000001 #
bUUUUUUUUUUUUUU $
0%
b0000001 &
bUUUUUUUUUUUUUU '
#50000000
1"
b00000000000001 $
1%
b00000000000001 '
#100000000
0"
b0000010 #
0%
b0000010 &
#150000000
1"
b00000000000010 $
1%
b00000000000010 '
#200000000
0"
b0000011 #
0%
b0000011 &
#250000000
1"
b00000000000100 $
1%
b00000000000100 '
#300000000
0"
b0000100 #
0%
b0000100 &
#350000000
1"
b00000000001000 $
1%
b00000000001000 '
#400000000
0"
b0000101 #
0%
b0000101 &
#450000000
1"
b00000000010000 $
1%
b00000000010000 '
#500000000
0"
b0000110 #
0%
b0000110 &
#550000000
1"
b00000000100000 $
1%
b00000000100000 '
#600000000
0"
b0000111 #
0%
b0000111 &
#650000000
1"
b00000001000000 $
1%
b00000001000000 '
#700000000
0"
b0010000 #
0%
b0010000 &
#750000000
1"
b00000000000000 $
1%
b00000000000000 '
#800000000
0"
b0010001 #
0%
b0010001 &
#850000000
1"
1%
#900000000
0"
b0010010 #
0%
b0010010 &
