state_machine.vhd
library ieee;
use ieee.std_logic_1164.all;
use ieee.numeric_std.all;

entity state_machine is
    port(
        clk : in std_logic;
        rst : in std_logic;
        state : out std_logic
    );
end entity;

architecture a_state_machine of state_machine is
    signal internal_state: std_logic;
begin
    process(clk,rst)
    begin
        if rst='1' then
            internal_state <= '0';
        elsif rising_edge(clk) then
            internal_state <= not internal_state;
        end if;
    end process;

    state <= internal_state;
end architecture;

state_machine_tb.vhd
library ieee;
use ieee.std_logic_1164.all;
use ieee.numeric_std.all;

entity state_machine_tb is
end;

architecture a_state_machine_tb of state_machine_tb is
    component state_machine is
        port
        (
            clk : in std_logic;
            rst : in std_logic;
            state : out std_logic
        );
    end component;
    constant period_time : time := 100 ns; -- tempo do clock
    signal finished : std_logic := '0'; -- booleano para indicar se o processo acabou
    signal clk, rst, state : std_logic; -- clock, reset, state
begin
    uut: state_machine
    port map
    (
        clk      => clk,
        rst      => rst,
        state    => state
    );
    
    reset_global: process -- a cada duas vezes o período reseta o registro
    begin
        rst <= '1';
        wait for period_time*2;
        rst <= '0';
        wait;
    end process;
    
    sim_time_proc: process
    begin
        wait for 10 us; -- tempo de simulação
        finished <= '1';
        wait;
    end process sim_time_proc;
    
    clk_proc: process
    begin
        while finished /= '1' loop -- gera clock até que sim_time_proc termine
            clk <= '0';
            wait for period_time / 2;
            clk <= '1';
            wait for period_time / 2; -- subida
        end loop;
        wait;
    end process clk_proc;
    
    process -- teste
    begin
        wait;
    end process;
    
end architecture;

state_machine_tb.vcd
$date
  Tue May  3 21:34:22 2022
$end
$version
  GHDL v0
$end
$timescale
  1 fs
$end
$scope module standard $end
$upscope $end
$scope module textio $end
$upscope $end
$scope module std_logic_1164 $end
$upscope $end
$scope module numeric_std $end
$upscope $end
$scope module state_machine_tb $end
$var reg 1 ! finished $end
$var reg 1 " clk $end
$var reg 1 # rst $end
$var reg 1 $ state $end
$scope module uut $end
$var reg 1 % clk $end
$var reg 1 & rst $end
$var reg 1 ' state $end
$var reg 1 ( internal_state $end
$upscope $end
$upscope $end
$enddefinitions $end
#0
0!
0"
1#
0$
0%
1&
0'
0(
#50000000
1"
1%
#100000000
0"
0%
#150000000
1"
1%
#200000000
0"
0#
0%
0&
#250000000
1"
1$
1%
1'
1(
#300000000
0"
0%
#350000000
1"
0$
1%
0'
0(
#400000000
0"
0%
#450000000
1"
1$
1%
1'
1(
#500000000
0"
0%
#550000000
1"
0$
1%
0'
0(
#600000000
0"
0%
#650000000
1"
1$
1%
1'
1(
#700000000
0"
0%
#750000000
1"
0$
1%
0'
0(
#800000000
0"
0%
#850000000
1"
1$
1%
1'
1(
#900000000
0"
0%
#950000000
1"
0$
1%
0'
0(
#1000000000
0"
0%
#1050000000
1"
1$
1%
1'
1(
#1100000000
0"
0%
#1150000000
1"
0$
1%
0'
0(
#1200000000
0"
0%
#1250000000
1"
1$
1%
1'
1(
#1300000000
0"
0%
#1350000000
1"
0$
1%
0'
0(
#1400000000
0"
0%
#1450000000
1"
1$
1%
1'
1(
#1500000000
0"
0%
#1550000000
1"
0$
1%
0'
0(
#1600000000
0"
0%
#1650000000
1"
1$
1%
1'
1(
#1700000000
0"
0%
#1750000000
1"
0$
1%
0'
0(
#1800000000
0"
0%
#1850000000
1"
1$
1%
1'
1(
#1900000000
0"
0%
#1950000000
1"
0$
1%
0'
0(
#2000000000
0"
0%
#2050000000
1"
1$
1%
1'
1(
#2100000000
0"
0%
#2150000000
1"
0$
1%
0'
0(
#2200000000
0"
0%
#2250000000
1"
1$
1%
1'
1(
#2300000000
0"
0%
#2350000000
1"
0$
1%
0'
0(
#2400000000
0"
0%
#2450000000
1"
1$
1%
1'
1(
#2500000000
0"
0%
#2550000000
1"
0$
1%
0'
0(
#2600000000
0"
0%
#2650000000
1"
1$
1%
1'
1(
#2700000000
0"
0%
#2750000000
1"
0$
1%
0'
0(
#2800000000
0"
0%
#2850000000
1"
1$
1%
1'
1(
#2900000000
0"
0%
#2950000000
1"
0$
1%
0'
0(
#3000000000
0"
0%
#3050000000
1"
1$
1%
1'
1(
#3100000000
0"
0%
#3150000000
1"
0$
1%
0'
0(
#3200000000
0"
0%
#3250000000
1"
1$
1%
1'
1(
#3300000000
0"
0%
#3350000000
1"
0$
1%
0'
0(
#3400000000
0"
0%
#3450000000
1"
1$
1%
1'
1(
#3500000000
0"
0%
#3550000000
1"
0$
1%
0'
0(
#3600000000
0"
0%
#3650000000
1"
1$
1%
1'
1(
#3700000000
0"
0%
#3750000000
1"
0$
1%
0'
0(
#3800000000
0"
0%
#3850000000
1"
1$
1%
1'
1(
#3900000000
0"
0%
#3950000000
1"
0$
1%
0'
0(
#4000000000
0"
0%
#4050000000
1"
1$
1%
1'
1(
#4100000000
0"
0%
#4150000000
1"
0$
1%
0'
0(
#4200000000
0"
0%
#4250000000
1"
1$
1%
1'
1(
#4300000000
0"
0%
#4350000000
1"
0$
1%
0'
0(
#4400000000
0"
0%
#4450000000
1"
1$
1%
1'
1(
#4500000000
0"
0%
#4550000000
1"
0$
1%
0'
0(
#4600000000
0"
0%
#4650000000
1"
1$
1%
1'
1(
#4700000000
0"
0%
#4750000000
1"
0$
1%
0'
0(
#4800000000
0"
0%
#4850000000
1"
1$
1%
1'
1(
#4900000000
0"
0%
#4950000000
1"
0$
1%
0'
0(
#5000000000
0"
0%
#5050000000
1"
1$
1%
1'
1(
#5100000000
0"
0%
#5150000000
1"
0$
1%
0'
0(
#5200000000
0"
0%
#5250000000
1"
1$
1%
1'
1(
#5300000000
0"
0%
#5350000000
1"
0$
1%
0'
0(
#5400000000
0"
0%
#5450000000
1"
1$
1%
1'
1(
#5500000000
0"
0%
#5550000000
1"
0$
1%
0'
0(
#5600000000
0"
0%
#5650000000
1"
1$
1%
1'
1(
#5700000000
0"
0%
#5750000000
1"
0$
1%
0'
0(
#5800000000
0"
0%
#5850000000
1"
1$
1%
1'
1(
#5900000000
0"
0%
#5950000000
1"
0$
1%
0'
0(
#6000000000
0"
0%
#6050000000
1"
1$
1%
1'
1(
#6100000000
0"
0%
#6150000000
1"
0$
1%
0'
0(
#6200000000
0"
0%
#6250000000
1"
1$
1%
1'
1(
#6300000000
0"
0%
#6350000000
1"
0$
1%
0'
0(
#6400000000
0"
0%
#6450000000
1"
1$
1%
1'
1(
#6500000000
0"
0%
#6550000000
1"
0$
1%
0'
0(
#6600000000
0"
0%
#6650000000
1"
1$
1%
1'
1(
#6700000000
0"
0%
#6750000000
1"
0$
1%
0'
0(
#6800000000
0"
0%
#6850000000
1"
1$
1%
1'
1(
#6900000000
0"
0%
#6950000000
1"
0$
1%
0'
0(
#7000000000
0"
0%
#7050000000
1"
1$
1%
1'
1(
#7100000000
0"
0%
#7150000000
1"
0$
1%
0'
0(
#7200000000
0"
0%
#7250000000
1"
1$
1%
1'
1(
#7300000000
0"
0%
#7350000000
1"
0$
1%
0'
0(
#7400000000
0"
0%
#7450000000
1"
1$
1%
1'
1(
#7500000000
0"
0%
#7550000000
1"
0$
1%
0'
0(
#7600000000
0"
0%
#7650000000
1"
1$
1%
1'
1(
#7700000000
0"
0%
#7750000000
1"
0$
1%
0'
0(
#7800000000
0"
0%
#7850000000
1"
1$
1%
1'
1(
#7900000000
0"
0%
#7950000000
1"
0$
1%
0'
0(
#8000000000
0"
0%
#8050000000
1"
1$
1%
1'
1(
#8100000000
0"
0%
#8150000000
1"
0$
1%
0'
0(
#8200000000
0"
0%
#8250000000
1"
1$
1%
1'
1(
#8300000000
0"
0%
#8350000000
1"
0$
1%
0'
0(
#8400000000
0"
0%
#8450000000
1"
1$
1%
1'
1(
#8500000000
0"
0%
#8550000000
1"
0$
1%
0'
0(
#8600000000
0"
0%
#8650000000
1"
1$
1%
1'
1(
#8700000000
0"
0%
#8750000000
1"
0$
1%
0'
0(
#8800000000
0"
0%
#8850000000
1"
1$
1%
1'
1(
#8900000000
0"
0%
#8950000000
1"
0$
1%
0'
0(
#9000000000
0"
0%
#9050000000
1"
1$
1%
1'
1(
#9100000000
0"
0%
#9150000000
1"
0$
1%
0'
0(
#9200000000
0"
0%
#9250000000
1"
1$
1%
1'
1(
#9300000000
0"
0%
#9350000000
1"
0$
1%
0'
0(
#9400000000
0"
0%
#9450000000
1"
1$
1%
1'
1(
#9500000000
0"
0%
#9550000000
1"
0$
1%
0'
0(
#9600000000
0"
0%
#9650000000
1"
1$
1%
1'
1(
#9700000000
0"
0%
#9750000000
1"
0$
1%
0'
0(
#9800000000
0"
0%
#9850000000
1"
1$
1%
1'
1(
#9900000000
0"
0%
#9950000000
1"
0$
1%
0'
0(
#10000000000
1!
0"
0%
#10050000000
1"
1$
1%
1'
1(
