state_machine.vhd
library ieee;
use ieee.std_logic_1164.all;
use ieee.numeric_std.all;

entity state_machine is
    port(
        clk : in std_logic;
        rst : in std_logic;
        state : out std_logic
    );
end entity;

architecture a_state_machine of state_machine is
    signal internal_state: std_logic;
begin
    process(clk,rst)
    begin
        if rst='1' then
            internal_state <= '0';
        elsif rising_edge(clk) then
            internal_state <= not internal_state;
        end if;
    end process;

    state <= internal_state;
end architecture;

reg16bits.vhd
library ieee;
use ieee.std_logic_1164.all;
use ieee.numeric_std.all;

entity reg16bits is
    port(
        clk : in std_logic;
        rst : in std_logic;
        wr_en : in std_logic;
        data_in : in unsigned(15 downto 0);
        data_out : out unsigned(15 downto 0)
    );
end entity;

architecture a_reg16bits of reg16bits is
    signal reg: unsigned(15 downto 0);
begin
    process(clk,rst,wr_en)
    begin
        if rst='1' then
            reg <= "0000000000000000";
        elsif wr_en='1' then
            if rising_edge(clk) then
                reg <= data_in;
            end if;
        end if;
    end process;

    data_out <= reg;
end architecture;

uc.vhd
library ieee;
use ieee.std_logic_1164.all;
use ieee.numeric_std.all;

entity uc is
    port(
        clk : IN  std_logic;
        rst : IN  std_logic;
        instruction : IN unsigned (14 downto 0);
        PC: OUT unsigned(15 downto 0)
    );
end entity uc;

architecture a_uc of uc is
    component reg16bits is
        port
        (
            clk      : IN std_logic ;
            rst      : IN std_logic ;
            wr_en    : IN std_logic ;
            data_in  : IN unsigned (15 downto 0);
            data_out : OUT unsigned (15 downto 0)
        );
    end component;
    
    component state_machine is
        port
        (
            clk : in std_logic;
            rst : in std_logic;
            state : out std_logic
        );
    end component state_machine;

    
    signal PC_in, PC_out : unsigned(15 downto 0);
    signal opcode : unsigned(3 downto 0);
    signal state, PC_wr_en, jump_en : std_logic;
    
begin
    PC_reg: reg16bits
    port map
    (
        clk      => clk,
        rst      => rst,
        wr_en    => PC_wr_en,
        data_in  => PC_in,
        data_out => PC_out
    );
    
    stateMachine: state_machine
    port map
    (
        clk   => clk,
        rst   => rst,
        state => state
    );

    PC_wr_en <= state;
    
    opcode <= instruction(14 downto 11); -- AVERIGUAR

    jump_en <= '1' when opcode = "1111" else
    '0';

    PC_in <= PC_out(15 downto 11) & instruction (10 downto 0) when jump_en = '1' else
    PC_in + "0000000000000001";
    
    PC <= PC_in;
    
end architecture a_uc;

uc_tb.vhd
library ieee;
use ieee.std_logic_1164.all;
use ieee.numeric_std.all;

entity uc_tb is
end;

architecture a_uc_tb of uc_tb is
    component uc is
        port
        (
            clk : IN  std_logic;
            rst : IN  std_logic;
            instruction : IN unsigned (14 downto 0);
            PC: OUT unsigned(15 downto 0)
        );
    end component;
    
    constant period_time : time := 100 ns;
    signal finished : std_logic := '0';
    
    signal clk, rst: std_logic;
    signal instruction : unsigned (14 downto 0);
    signal PC : unsigned(15 downto 0);
    
begin
    uut : uc
    port map
    (
        clk         => clk,
        rst         => rst,
        instruction => instruction,
        PC          => PC
    );

    reset_global: process
    begin
        rst <= '1';
        wait for period_time*2;
        rst <= '0';
        wait;
    end process reset_global;
    
    sim_time_proc: process
    begin
        wait for 100 us;
        finished <= '1';
        wait;
    end process sim_time_proc;
    
    clk_proc: process
    begin
        while finished /= '1' loop
            clk <= '0';
            wait for period_time / 2;
            clk <= '1';
            wait for period_time / 2;
        end loop;
        wait;
    end process clk_proc;
    
    process
    begin
        
        instruction <= "000000000000000";
        wait for period_time * 22;
        
        instruction <= "111101100100001";
        wait for period_time * 2;
        
        instruction <= "000000000000000";
        wait;
        
    end process;
    
end architecture a_uc_tb;

uc_tb.vcd
$date
  Wed May  4 19:14:45 2022
$end
$version
  GHDL v0
$end
$timescale
  1 fs
$end
$scope module standard $end
$upscope $end
$scope module textio $end
$upscope $end
$scope module std_logic_1164 $end
$upscope $end
$scope module numeric_std $end
$upscope $end
$scope module uc_tb $end
$var reg 1 ! finished $end
$var reg 1 " clk $end
$var reg 1 # rst $end
$var reg 15 $ instruction[14:0] $end
$var reg 16 % pc[15:0] $end
$scope module uut $end
$var reg 1 & clk $end
$var reg 1 ' rst $end
$var reg 15 ( instruction[14:0] $end
$var reg 16 ) pc[15:0] $end
$var reg 16 * pc_in[15:0] $end
$var reg 16 + pc_out[15:0] $end
$var reg 4 , opcode[3:0] $end
$var reg 1 - state $end
$var reg 1 . pc_wr_en $end
$var reg 1 / jump_en $end
$scope module pc_reg $end
$var reg 1 0 clk $end
$var reg 1 1 rst $end
$var reg 1 2 wr_en $end
$var reg 16 3 data_in[15:0] $end
$var reg 16 4 data_out[15:0] $end
$var reg 16 5 reg[15:0] $end
$upscope $end
$scope module statemachine $end
$var reg 1 6 clk $end
$var reg 1 7 rst $end
$var reg 1 8 state $end
$var reg 1 9 internal_state $end
$upscope $end
$upscope $end
$upscope $end
$enddefinitions $end
#0
0!
0"
1#
b000000000000000 $
bXXXXXXXXXXXXXXXX %
0&
1'
b000000000000000 (
bXXXXXXXXXXXXXXXX )
bXXXXXXXXXXXXXXXX *
b0000000000000000 +
b0000 ,
0-
0.
0/
00
11
12
bXXXXXXXXXXXXXXXX 3
b0000000000000000 4
b0000000000000000 5
06
17
08
09
#50000000
1"
1&
10
16
#100000000
0"
0&
00
06
#150000000
1"
1&
10
16
#200000000
0"
0#
0&
0'
00
01
06
07
#250000000
1"
1&
bXXXXXXXXXXXXXXXX +
1-
1.
10
bXXXXXXXXXXXXXXXX 4
bXXXXXXXXXXXXXXXX 5
16
18
19
#300000000
0"
0&
00
06
#350000000
1"
1&
0-
0.
10
16
08
09
#400000000
0"
0&
00
06
#450000000
1"
1&
1-
1.
10
16
18
19
#500000000
0"
0&
00
06
#550000000
1"
1&
0-
0.
10
16
08
09
#600000000
0"
0&
00
06
#650000000
1"
1&
1-
1.
10
16
18
19
#700000000
0"
0&
00
06
#750000000
1"
1&
0-
0.
10
16
08
09
#800000000
0"
0&
00
06
#850000000
1"
1&
1-
1.
10
16
18
19
#900000000
0"
0&
00
06
#950000000
1"
1&
0-
0.
10
16
08
09
#1000000000
0"
0&
00
06
#1050000000
1"
1&
1-
1.
10
16
18
19
#1100000000
0"
0&
00
06
#1150000000
1"
1&
0-
0.
10
16
08
09
#1200000000
0"
0&
00
06
#1250000000
1"
1&
1-
1.
10
16
18
19
#1300000000
0"
0&
00
06
#1350000000
1"
1&
0-
0.
10
16
08
09
#1400000000
0"
0&
00
06
#1450000000
1"
1&
1-
1.
10
16
18
19
#1500000000
0"
0&
00
06
#1550000000
1"
1&
0-
0.
10
16
08
09
#1600000000
0"
0&
00
06
#1650000000
1"
1&
1-
1.
10
16
18
19
#1700000000
0"
0&
00
06
#1750000000
1"
1&
0-
0.
10
16
08
09
#1800000000
0"
0&
00
06
#1850000000
1"
1&
1-
1.
10
16
18
19
#1900000000
0"
0&
00
06
#1950000000
1"
1&
0-
0.
10
16
08
09
#2000000000
0"
b101101101101111 $
bXXXXX01101101111 %
0&
b101101101101111 (
bXXXXX01101101111 )
bXXXXX01101101111 *
b1111 ,
1/
00
bXXXXX01101101111 3
06
#2050000000
1"
1&
bXXXXX01101101111 +
1-
1.
10
bXXXXX01101101111 4
bXXXXX01101101111 5
16
18
19
#2100000000
0"
0&
00
06
#2150000000
1"
1&
0-
0.
10
16
08
09
#2200000000
0"
0&
00
06
#2250000000
1"
1&
1-
1.
10
16
18
19
#2300000000
0"
0&
00
06
#2350000000
1"
1&
0-
0.
10
16
08
09
#2400000000
0"
b000000000000000 $
bXXXXXXXXXXXXXXXX %
0&
b000000000000000 (
bXXXXXXXXXXXXXXXX )
bXXXXXXXXXXXXXXXX *
b0000 ,
0/
00
bXXXXXXXXXXXXXXXX 3
06
#2450000000
1"
1&
bXXXXXXXXXXXXXXXX +
1-
1.
10
bXXXXXXXXXXXXXXXX 4
bXXXXXXXXXXXXXXXX 5
16
18
19
#2500000000
0"
0&
00
06
#2550000000
1"
1&
0-
0.
10
16
08
09
#2600000000
0"
0&
00
06
#2650000000
1"
1&
1-
1.
10
16
18
19
#2700000000
0"
0&
00
06
#2750000000
1"
1&
0-
0.
10
16
08
09
#2800000000
0"
0&
00
06
#2850000000
1"
1&
1-
1.
10
16
18
19
#2900000000
0"
0&
00
06
#2950000000
1"
1&
0-
0.
10
16
08
09
#3000000000
0"
0&
00
06
#3050000000
1"
1&
1-
1.
10
16
18
19
#3100000000
0"
0&
00
06
#3150000000
1"
1&
0-
0.
10
16
08
09
#3200000000
0"
0&
00
06
#3250000000
1"
1&
1-
1.
10
16
18
19
#3300000000
0"
0&
00
06
#3350000000
1"
1&
0-
0.
10
16
08
09
#3400000000
0"
0&
00
06
#3450000000
1"
1&
1-
1.
10
16
18
19
#3500000000
0"
0&
00
06
#3550000000
1"
1&
0-
0.
10
16
08
09
#3600000000
0"
0&
00
06
#3650000000
1"
1&
1-
1.
10
16
18
19
#3700000000
0"
0&
00
06
#3750000000
1"
1&
0-
0.
10
16
08
09
#3800000000
0"
0&
00
06
#3850000000
1"
1&
1-
1.
10
16
18
19
#3900000000
0"
0&
00
06
#3950000000
1"
1&
0-
0.
10
16
08
09
#4000000000
0"
0&
00
06
#4050000000
1"
1&
1-
1.
10
16
18
19
#4100000000
0"
0&
00
06
#4150000000
1"
1&
0-
0.
10
16
08
09
#4200000000
0"
0&
00
06
#4250000000
1"
1&
1-
1.
10
16
18
19
#4300000000
0"
0&
00
06
#4350000000
1"
1&
0-
0.
10
16
08
09
#4400000000
0"
0&
00
06
#4450000000
1"
1&
1-
1.
10
16
18
19
#4500000000
0"
0&
00
06
#4550000000
1"
1&
0-
0.
10
16
08
09
#4600000000
0"
0&
00
06
#4650000000
1"
1&
1-
1.
10
16
18
19
#4700000000
0"
0&
00
06
#4750000000
1"
1&
0-
0.
10
16
08
09
#4800000000
0"
0&
00
06
#4850000000
1"
1&
1-
1.
10
16
18
19
#4900000000
0"
0&
00
06
#4950000000
1"
1&
0-
0.
10
16
08
09
#5000000000
0"
0&
00
06
#5050000000
1"
1&
1-
1.
10
16
18
19
#5100000000
0"
0&
00
06
#5150000000
1"
1&
0-
0.
10
16
08
09
#5200000000
0"
0&
00
06
#5250000000
1"
1&
1-
1.
10
16
18
19
#5300000000
0"
0&
00
06
#5350000000
1"
1&
0-
0.
10
16
08
09
#5400000000
0"
0&
00
06
#5450000000
1"
1&
1-
1.
10
16
18
19
#5500000000
0"
0&
00
06
#5550000000
1"
1&
0-
0.
10
16
08
09
#5600000000
0"
0&
00
06
#5650000000
1"
1&
1-
1.
10
16
18
19
#5700000000
0"
0&
00
06
#5750000000
1"
1&
0-
0.
10
16
08
09
#5800000000
0"
0&
00
06
#5850000000
1"
1&
1-
1.
10
16
18
19
#5900000000
0"
0&
00
06
#5950000000
1"
1&
0-
0.
10
16
08
09
#6000000000
0"
0&
00
06
#6050000000
1"
1&
1-
1.
10
16
18
19
#6100000000
0"
0&
00
06
#6150000000
1"
1&
0-
0.
10
16
08
09
#6200000000
0"
0&
00
06
#6250000000
1"
1&
1-
1.
10
16
18
19
#6300000000
0"
0&
00
06
#6350000000
1"
1&
0-
0.
10
16
08
09
#6400000000
0"
0&
00
06
#6450000000
1"
1&
1-
1.
10
16
18
19
#6500000000
0"
0&
00
06
#6550000000
1"
1&
0-
0.
10
16
08
09
#6600000000
0"
0&
00
06
#6650000000
1"
1&
1-
1.
10
16
18
19
#6700000000
0"
0&
00
06
#6750000000
1"
1&
0-
0.
10
16
08
09
#6800000000
0"
0&
00
06
#6850000000
1"
1&
1-
1.
10
16
18
19
#6900000000
0"
0&
00
06
#6950000000
1"
1&
0-
0.
10
16
08
09
#7000000000
0"
0&
00
06
#7050000000
1"
1&
1-
1.
10
16
18
19
#7100000000
0"
0&
00
06
#7150000000
1"
1&
0-
0.
10
16
08
09
#7200000000
0"
0&
00
06
#7250000000
1"
1&
1-
1.
10
16
18
19
#7300000000
0"
0&
00
06
#7350000000
1"
1&
0-
0.
10
16
08
09
#7400000000
0"
0&
00
06
#7450000000
1"
1&
1-
1.
10
16
18
19
#7500000000
0"
0&
00
06
#7550000000
1"
1&
0-
0.
10
16
08
09
#7600000000
0"
0&
00
06
#7650000000
1"
1&
1-
1.
10
16
18
19
#7700000000
0"
0&
00
06
#7750000000
1"
1&
0-
0.
10
16
08
09
#7800000000
0"
0&
00
06
#7850000000
1"
1&
1-
1.
10
16
18
19
#7900000000
0"
0&
00
06
#7950000000
1"
1&
0-
0.
10
16
08
09
#8000000000
0"
0&
00
06
#8050000000
1"
1&
1-
1.
10
16
18
19
#8100000000
0"
0&
00
06
#8150000000
1"
1&
0-
0.
10
16
08
09
#8200000000
0"
0&
00
06
#8250000000
1"
1&
1-
1.
10
16
18
19
#8300000000
0"
0&
00
06
#8350000000
1"
1&
0-
0.
10
16
08
09
#8400000000
0"
0&
00
06
#8450000000
1"
1&
1-
1.
10
16
18
19
#8500000000
0"
0&
00
06
#8550000000
1"
1&
0-
0.
10
16
08
09
#8600000000
0"
0&
00
06
#8650000000
1"
1&
1-
1.
10
16
18
19
#8700000000
0"
0&
00
06
#8750000000
1"
1&
0-
0.
10
16
08
09
#8800000000
0"
0&
00
06
#8850000000
1"
1&
1-
1.
10
16
18
19
#8900000000
0"
0&
00
06
#8950000000
1"
1&
0-
0.
10
16
08
09
#9000000000
0"
0&
00
06
#9050000000
1"
1&
1-
1.
10
16
18
19
#9100000000
0"
0&
00
06
#9150000000
1"
1&
0-
0.
10
16
08
09
#9200000000
0"
0&
00
06
#9250000000
1"
1&
1-
1.
10
16
18
19
#9300000000
0"
0&
00
06
#9350000000
1"
1&
0-
0.
10
16
08
09
#9400000000
0"
0&
00
06
#9450000000
1"
1&
1-
1.
10
16
18
19
#9500000000
0"
0&
00
06
#9550000000
1"
1&
0-
0.
10
16
08
09
#9600000000
0"
0&
00
06
#9650000000
1"
1&
1-
1.
10
16
18
19
#9700000000
0"
0&
00
06
#9750000000
1"
1&
0-
0.
10
16
08
09
#9800000000
0"
0&
00
06
#9850000000
1"
1&
1-
1.
10
16
18
19
#9900000000
0"
0&
00
06
#9950000000
1"
1&
0-
0.
10
16
08
09
#10000000000
0"
0&
00
06
#10050000000
1"
1&
1-
1.
10
16
18
19
#10100000000
0"
0&
00
06
#10150000000
1"
1&
0-
0.
10
16
08
09
#10200000000
0"
0&
00
06
#10250000000
1"
1&
1-
1.
10
16
18
19
#10300000000
0"
0&
00
06
#10350000000
1"
1&
0-
0.
10
16
08
09
#10400000000
0"
0&
00
06
#10450000000
1"
1&
1-
1.
10
16
18
19
#10500000000
0"
0&
00
06
#10550000000
1"
1&
0-
0.
10
16
08
09
#10600000000
0"
0&
00
06
#10650000000
1"
1&
1-
1.
10
16
18
19
#10700000000
0"
0&
00
06
#10750000000
1"
1&
0-
0.
10
16
08
09
#10800000000
0"
0&
00
06
#10850000000
1"
1&
1-
1.
10
16
18
19
#10900000000
0"
0&
00
06
#10950000000
1"
1&
0-
0.
10
16
08
09
#11000000000
0"
0&
00
06
#11050000000
1"
1&
1-
1.
10
16
18
19
#11100000000
0"
0&
00
06
#11150000000
1"
1&
0-
0.
10
16
08
09
#11200000000
0"
0&
00
06
#11250000000
1"
1&
1-
1.
10
16
18
19
#11300000000
0"
0&
00
06
#11350000000
1"
1&
0-
0.
10
16
08
09
#11400000000
0"
0&
00
06
#11450000000
1"
1&
1-
1.
10
16
18
19
#11500000000
0"
0&
00
06
#11550000000
1"
1&
0-
0.
10
16
08
09
#11600000000
0"
0&
00
06
#11650000000
1"
1&
1-
1.
10
16
18
19
#11700000000
0"
0&
00
06
#11750000000
1"
1&
0-
0.
10
16
08
09
#11800000000
0"
0&
00
06
#11850000000
1"
1&
1-
1.
10
16
18
19
#11900000000
0"
0&
00
06
#11950000000
1"
1&
0-
0.
10
16
08
09
#12000000000
0"
0&
00
06
#12050000000
1"
1&
1-
1.
10
16
18
19
#12100000000
0"
0&
00
06
#12150000000
1"
1&
0-
0.
10
16
08
09
#12200000000
0"
0&
00
06
#12250000000
1"
1&
1-
1.
10
16
18
19
#12300000000
0"
0&
00
06
#12350000000
1"
1&
0-
0.
10
16
08
09
#12400000000
0"
0&
00
06
#12450000000
1"
1&
1-
1.
10
16
18
19
#12500000000
0"
0&
00
06
#12550000000
1"
1&
0-
0.
10
16
08
09
#12600000000
0"
0&
00
06
#12650000000
1"
1&
1-
1.
10
16
18
19
#12700000000
0"
0&
00
06
#12750000000
1"
1&
0-
0.
10
16
08
09
#12800000000
0"
0&
00
06
#12850000000
1"
1&
1-
1.
10
16
18
19
#12900000000
0"
0&
00
06
#12950000000
1"
1&
0-
0.
10
16
08
09
#13000000000
0"
0&
00
06
#13050000000
1"
1&
1-
1.
10
16
18
19
#13100000000
0"
0&
00
06
#13150000000
1"
1&
0-
0.
10
16
08
09
#13200000000
0"
0&
00
06
#13250000000
1"
1&
1-
1.
10
16
18
19
#13300000000
0"
0&
00
06
#13350000000
1"
1&
0-
0.
10
16
08
09
#13400000000
0"
0&
00
06
#13450000000
1"
1&
1-
1.
10
16
18
19
#13500000000
0"
0&
00
06
#13550000000
1"
1&
0-
0.
10
16
08
09
#13600000000
0"
0&
00
06
#13650000000
1"
1&
1-
1.
10
16
18
19
#13700000000
0"
0&
00
06
#13750000000
1"
1&
0-
0.
10
16
08
09
#13800000000
0"
0&
00
06
#13850000000
1"
1&
1-
1.
10
16
18
19
#13900000000
0"
0&
00
06
#13950000000
1"
1&
0-
0.
10
16
08
09
#14000000000
0"
0&
00
06
#14050000000
1"
1&
1-
1.
10
16
18
19
#14100000000
0"
0&
00
06
#14150000000
1"
1&
0-
0.
10
16
08
09
#14200000000
0"
0&
00
06
#14250000000
1"
1&
1-
1.
10
16
18
19
#14300000000
0"
0&
00
06
#14350000000
1"
1&
0-
0.
10
16
08
09
#14400000000
0"
0&
00
06
#14450000000
1"
1&
1-
1.
10
16
18
19
#14500000000
0"
0&
00
06
#14550000000
1"
1&
0-
0.
10
16
08
09
#14600000000
0"
0&
00
06
#14650000000
1"
1&
1-
1.
10
16
18
19
#14700000000
0"
0&
00
06
#14750000000
1"
1&
0-
0.
10
16
08
09
#14800000000
0"
0&
00
06
#14850000000
1"
1&
1-
1.
10
16
18
19
#14900000000
0"
0&
00
06
#14950000000
1"
1&
0-
0.
10
16
08
09
#15000000000
0"
0&
00
06
#15050000000
1"
1&
1-
1.
10
16
18
19
#15100000000
0"
0&
00
06
#15150000000
1"
1&
0-
0.
10
16
08
09
#15200000000
0"
0&
00
06
#15250000000
1"
1&
1-
1.
10
16
18
19
#15300000000
0"
0&
00
06
#15350000000
1"
1&
0-
0.
10
16
08
09
#15400000000
0"
0&
00
06
#15450000000
1"
1&
1-
1.
10
16
18
19
#15500000000
0"
0&
00
06
#15550000000
1"
1&
0-
0.
10
16
08
09
#15600000000
0"
0&
00
06
#15650000000
1"
1&
1-
1.
10
16
18
19
#15700000000
0"
0&
00
06
#15750000000
1"
1&
0-
0.
10
16
08
09
#15800000000
0"
0&
00
06
#15850000000
1"
1&
1-
1.
10
16
18
19
#15900000000
0"
0&
00
06
#15950000000
1"
1&
0-
0.
10
16
08
09
#16000000000
0"
0&
00
06
#16050000000
1"
1&
1-
1.
10
16
18
19
#16100000000
0"
0&
00
06
#16150000000
1"
1&
0-
0.
10
16
08
09
#16200000000
0"
0&
00
06
#16250000000
1"
1&
1-
1.
10
16
18
19
#16300000000
0"
0&
00
06
#16350000000
1"
1&
0-
0.
10
16
08
09
#16400000000
0"
0&
00
06
#16450000000
1"
1&
1-
1.
10
16
18
19
#16500000000
0"
0&
00
06
#16550000000
1"
1&
0-
0.
10
16
08
09
#16600000000
0"
0&
00
06
#16650000000
1"
1&
1-
1.
10
16
18
19
#16700000000
0"
0&
00
06
#16750000000
1"
1&
0-
0.
10
16
08
09
#16800000000
0"
0&
00
06
#16850000000
1"
1&
1-
1.
10
16
18
19
#16900000000
0"
0&
00
06
#16950000000
1"
1&
0-
0.
10
16
08
09
#17000000000
0"
0&
00
06
#17050000000
1"
1&
1-
1.
10
16
18
19
#17100000000
0"
0&
00
06
#17150000000
1"
1&
0-
0.
10
16
08
09
#17200000000
0"
0&
00
06
#17250000000
1"
1&
1-
1.
10
16
18
19
#17300000000
0"
0&
00
06
#17350000000
1"
1&
0-
0.
10
16
08
09
#17400000000
0"
0&
00
06
#17450000000
1"
1&
1-
1.
10
16
18
19
#17500000000
0"
0&
00
06
#17550000000
1"
1&
0-
0.
10
16
08
09
#17600000000
0"
0&
00
06
#17650000000
1"
1&
1-
1.
10
16
18
19
#17700000000
0"
0&
00
06
#17750000000
1"
1&
0-
0.
10
16
08
09
#17800000000
0"
0&
00
06
#17850000000
1"
1&
1-
1.
10
16
18
19
#17900000000
0"
0&
00
06
#17950000000
1"
1&
0-
0.
10
16
08
09
#18000000000
0"
0&
00
06
#18050000000
1"
1&
1-
1.
10
16
18
19
#18100000000
0"
0&
00
06
#18150000000
1"
1&
0-
0.
10
16
08
09
#18200000000
0"
0&
00
06
#18250000000
1"
1&
1-
1.
10
16
18
19
#18300000000
0"
0&
00
06
#18350000000
1"
1&
0-
0.
10
16
08
09
#18400000000
0"
0&
00
06
#18450000000
1"
1&
1-
1.
10
16
18
19
#18500000000
0"
0&
00
06
#18550000000
1"
1&
0-
0.
10
16
08
09
#18600000000
0"
0&
00
06
#18650000000
1"
1&
1-
1.
10
16
18
19
#18700000000
0"
0&
00
06
#18750000000
1"
1&
0-
0.
10
16
08
09
#18800000000
0"
0&
00
06
#18850000000
1"
1&
1-
1.
10
16
18
19
#18900000000
0"
0&
00
06
#18950000000
1"
1&
0-
0.
10
16
08
09
#19000000000
0"
0&
00
06
#19050000000
1"
1&
1-
1.
10
16
18
19
#19100000000
0"
0&
00
06
#19150000000
1"
1&
0-
0.
10
16
08
09
#19200000000
0"
0&
00
06
#19250000000
1"
1&
1-
1.
10
16
18
19
#19300000000
0"
0&
00
06
#19350000000
1"
1&
0-
0.
10
16
08
09
#19400000000
0"
0&
00
06
#19450000000
1"
1&
1-
1.
10
16
18
19
#19500000000
0"
0&
00
06
#19550000000
1"
1&
0-
0.
10
16
08
09
#19600000000
0"
0&
00
06
#19650000000
1"
1&
1-
1.
10
16
18
19
#19700000000
0"
0&
00
06
#19750000000
1"
1&
0-
0.
10
16
08
09
#19800000000
0"
0&
00
06
#19850000000
1"
1&
1-
1.
10
16
18
19
#19900000000
0"
0&
00
06
#19950000000
1"
1&
0-
0.
10
16
08
09
#20000000000
0"
0&
00
06
#20050000000
1"
1&
1-
1.
10
16
18
19
#20100000000
0"
0&
00
06
#20150000000
1"
1&
0-
0.
10
16
08
09
#20200000000
0"
0&
00
06
#20250000000
1"
1&
1-
1.
10
16
18
19
#20300000000
0"
0&
00
06
#20350000000
1"
1&
0-
0.
10
16
08
09
#20400000000
0"
0&
00
06
#20450000000
1"
1&
1-
1.
10
16
18
19
#20500000000
0"
0&
00
06
#20550000000
1"
1&
0-
0.
10
16
08
09
#20600000000
0"
0&
00
06
#20650000000
1"
1&
1-
1.
10
16
18
19
#20700000000
0"
0&
00
06
#20750000000
1"
1&
0-
0.
10
16
08
09
#20800000000
0"
0&
00
06
#20850000000
1"
1&
1-
1.
10
16
18
19
#20900000000
0"
0&
00
06
#20950000000
1"
1&
0-
0.
10
16
08
09
#21000000000
0"
0&
00
06
#21050000000
1"
1&
1-
1.
10
16
18
19
#21100000000
0"
0&
00
06
#21150000000
1"
1&
0-
0.
10
16
08
09
#21200000000
0"
0&
00
06
#21250000000
1"
1&
1-
1.
10
16
18
19
#21300000000
0"
0&
00
06
#21350000000
1"
1&
0-
0.
10
16
08
09
#21400000000
0"
0&
00
06
#21450000000
1"
1&
1-
1.
10
16
18
19
#21500000000
0"
0&
00
06
#21550000000
1"
1&
0-
0.
10
16
08
09
#21600000000
0"
0&
00
06
#21650000000
1"
1&
1-
1.
10
16
18
19
#21700000000
0"
0&
00
06
#21750000000
1"
1&
0-
0.
10
16
08
09
#21800000000
0"
0&
00
06
#21850000000
1"
1&
1-
1.
10
16
18
19
#21900000000
0"
0&
00
06
#21950000000
1"
1&
0-
0.
10
16
08
09
#22000000000
0"
0&
00
06
#22050000000
1"
1&
1-
1.
10
16
18
19
#22100000000
0"
0&
00
06
#22150000000
1"
1&
0-
0.
10
16
08
09
#22200000000
0"
0&
00
06
#22250000000
1"
1&
1-
1.
10
16
18
19
#22300000000
0"
0&
00
06
#22350000000
1"
1&
0-
0.
10
16
08
09
#22400000000
0"
0&
00
06
#22450000000
1"
1&
1-
1.
10
16
18
19
#22500000000
0"
0&
00
06
#22550000000
1"
1&
0-
0.
10
16
08
09
#22600000000
0"
0&
00
06
#22650000000
1"
1&
1-
1.
10
16
18
19
#22700000000
0"
0&
00
06
#22750000000
1"
1&
0-
0.
10
16
08
09
#22800000000
0"
0&
00
06
#22850000000
1"
1&
1-
1.
10
16
18
19
#22900000000
0"
0&
00
06
#22950000000
1"
1&
0-
0.
10
16
08
09
#23000000000
0"
0&
00
06
#23050000000
1"
1&
1-
1.
10
16
18
19
#23100000000
0"
0&
00
06
#23150000000
1"
1&
0-
0.
10
16
08
09
#23200000000
0"
0&
00
06
#23250000000
1"
1&
1-
1.
10
16
18
19
#23300000000
0"
0&
00
06
#23350000000
1"
1&
0-
0.
10
16
08
09
#23400000000
0"
0&
00
06
#23450000000
1"
1&
1-
1.
10
16
18
19
#23500000000
0"
0&
00
06
#23550000000
1"
1&
0-
0.
10
16
08
09
#23600000000
0"
0&
00
06
#23650000000
1"
1&
1-
1.
10
16
18
19
#23700000000
0"
0&
00
06
#23750000000
1"
1&
0-
0.
10
16
08
09
#23800000000
0"
0&
00
06
#23850000000
1"
1&
1-
1.
10
16
18
19
#23900000000
0"
0&
00
06
#23950000000
1"
1&
0-
0.
10
16
08
09
#24000000000
0"
0&
00
06
#24050000000
1"
1&
1-
1.
10
16
18
19
#24100000000
0"
0&
00
06
#24150000000
1"
1&
0-
0.
10
16
08
09
#24200000000
0"
0&
00
06
#24250000000
1"
1&
1-
1.
10
16
18
19
#24300000000
0"
0&
00
06
#24350000000
1"
1&
0-
0.
10
16
08
09
#24400000000
0"
0&
00
06
#24450000000
1"
1&
1-
1.
10
16
18
19
#24500000000
0"
0&
00
06
#24550000000
1"
1&
0-
0.
10
16
08
09
#24600000000
0"
0&
00
06
#24650000000
1"
1&
1-
1.
10
16
18
19
#24700000000
0"
0&
00
06
#24750000000
1"
1&
0-
0.
10
16
08
09
#24800000000
0"
0&
00
06
#24850000000
1"
1&
1-
1.
10
16
18
19
#24900000000
0"
0&
00
06
#24950000000
1"
1&
0-
0.
10
16
08
09
#25000000000
0"
0&
00
06
#25050000000
1"
1&
1-
1.
10
16
18
19
#25100000000
0"
0&
00
06
#25150000000
1"
1&
0-
0.
10
16
08
09
#25200000000
0"
0&
00
06
#25250000000
1"
1&
1-
1.
10
16
18
19
#25300000000
0"
0&
00
06
#25350000000
1"
1&
0-
0.
10
16
08
09
#25400000000
0"
0&
00
06
#25450000000
1"
1&
1-
1.
10
16
18
19
#25500000000
0"
0&
00
06
#25550000000
1"
1&
0-
0.
10
16
08
09
#25600000000
0"
0&
00
06
#25650000000
1"
1&
1-
1.
10
16
18
19
#25700000000
0"
0&
00
06
#25750000000
1"
1&
0-
0.
10
16
08
09
#25800000000
0"
0&
00
06
#25850000000
1"
1&
1-
1.
10
16
18
19
#25900000000
0"
0&
00
06
#25950000000
1"
1&
0-
0.
10
16
08
09
#26000000000
0"
0&
00
06
#26050000000
1"
1&
1-
1.
10
16
18
19
#26100000000
0"
0&
00
06
#26150000000
1"
1&
0-
0.
10
16
08
09
#26200000000
0"
0&
00
06
#26250000000
1"
1&
1-
1.
10
16
18
19
#26300000000
0"
0&
00
06
#26350000000
1"
1&
0-
0.
10
16
08
09
#26400000000
0"
0&
00
06
#26450000000
1"
1&
1-
1.
10
16
18
19
#26500000000
0"
0&
00
06
#26550000000
1"
1&
0-
0.
10
16
08
09
#26600000000
0"
0&
00
06
#26650000000
1"
1&
1-
1.
10
16
18
19
#26700000000
0"
0&
00
06
#26750000000
1"
1&
0-
0.
10
16
08
09
#26800000000
0"
0&
00
06
#26850000000
1"
1&
1-
1.
10
16
18
19
#26900000000
0"
0&
00
06
#26950000000
1"
1&
0-
0.
10
16
08
09
#27000000000
0"
0&
00
06
#27050000000
1"
1&
1-
1.
10
16
18
19
#27100000000
0"
0&
00
06
#27150000000
1"
1&
0-
0.
10
16
08
09
#27200000000
0"
0&
00
06
#27250000000
1"
1&
1-
1.
10
16
18
19
#27300000000
0"
0&
00
06
#27350000000
1"
1&
0-
0.
10
16
08
09
#27400000000
0"
0&
00
06
#27450000000
1"
1&
1-
1.
10
16
18
19
#27500000000
0"
0&
00
06
#27550000000
1"
1&
0-
0.
10
16
08
09
#27600000000
0"
0&
00
06
#27650000000
1"
1&
1-
1.
10
16
18
19
#27700000000
0"
0&
00
06
#27750000000
1"
1&
0-
0.
10
16
08
09
#27800000000
0"
0&
00
06
#27850000000
1"
1&
1-
1.
10
16
18
19
#27900000000
0"
0&
00
06
#27950000000
1"
1&
0-
0.
10
16
08
09
#28000000000
0"
0&
00
06
#28050000000
1"
1&
1-
1.
10
16
18
19
#28100000000
0"
0&
00
06
#28150000000
1"
1&
0-
0.
10
16
08
09
#28200000000
0"
0&
00
06
#28250000000
1"
1&
1-
1.
10
16
18
19
#28300000000
0"
0&
00
06
#28350000000
1"
1&
0-
0.
10
16
08
09
#28400000000
0"
0&
00
06
#28450000000
1"
1&
1-
1.
10
16
18
19
#28500000000
0"
0&
00
06
#28550000000
1"
1&
0-
0.
10
16
08
09
#28600000000
0"
0&
00
06
#28650000000
1"
1&
1-
1.
10
16
18
19
#28700000000
0"
0&
00
06
#28750000000
1"
1&
0-
0.
10
16
08
09
#28800000000
0"
0&
00
06
