state_machine.vhd
library ieee;
use ieee.std_logic_1164.all;
use ieee.numeric_std.all;

entity state_machine is
    port(
        clk : in std_logic;
        rst : in std_logic;
        state : out unsigned(1 downto 0)
    );
end entity;

architecture a_state_machine of state_machine is
    signal internal_state: unsigned(1 downto 0);
begin
    process(clk,rst)
    begin
        if rst='1' then
            internal_state <= "00";
        elsif rising_edge(clk) then
            if (internal_state = "10") then
                internal_state <= "00";
            else
                internal_state <= internal_state + 1;
            end if;
        end if;
    end process;

    state <= internal_state;
end architecture;

reg14bits.vhd
library ieee;
use ieee.std_logic_1164.all;
use ieee.numeric_std.all;

entity reg14bits is
    port(
        clk : in std_logic;
        rst : in std_logic;
        wr_en : in std_logic;
        data_in : in unsigned(13 downto 0);
        data_out : out unsigned(13 downto 0)
    );
end entity;

architecture a_reg14bits of reg14bits is
    signal reg: unsigned(13 downto 0);
begin
    process(clk,rst,wr_en)
    begin
        if rst='1' then
            reg <= "00000000000000";
        elsif wr_en='1' then
            if rising_edge(clk) then
                reg <= data_in;
            end if;
        end if;
    end process;

    data_out <= reg;
end architecture;

uc.vhd
library ieee;
use ieee.std_logic_1164.all;
use ieee.numeric_std.all;

entity uc is
    port(
        clk : IN  std_logic;
        rst : IN  std_logic;
        instruction_in : IN unsigned (13 downto 0);
        instruction_out : OUT unsigned (13 downto 0);
        PC: OUT unsigned(13 downto 0);
        fetch: OUT std_logic; -- booleano para dizer se esta em fetch
        decode: OUT std_logic; -- booleano para dizer se esta em decode
        execute: OUT std_logic; -- booleano para dizer se esta em execute
        state: OUT unsigned(1 downto 0) -- booleano para dizer em que etapa esta a maquina de estados
    );
end entity uc;

architecture a_uc of uc is
    component reg14bits is
        port
        (
            clk      : IN std_logic ;
            rst      : IN std_logic ;
            wr_en    : IN std_logic ;
            data_in  : IN unsigned (13 downto 0);
            data_out : OUT unsigned (13 downto 0)
        );
    end component;

    component state_machine is
        port
        (
            clk : in std_logic;
            rst : in std_logic;
            state : out unsigned(1 downto 0)
        );
    end component state_machine;
    
    signal PC_reg_in, PC_reg_out : unsigned(13 downto 0); -- input e output do program counter
    signal opcode : unsigned(3 downto 0); -- opcode -> add, jump, nop, etc
    signal PC_reg_wr_en, instruction_reg_wr_en, jump_en : std_logic; -- enables = permite escrever nos registradores ou fazer jump
    -- middlware signal para saidas
    signal instruction_out_internal : unsigned(13 downto 0); -- estado da maquina de estados
    signal state_internal : unsigned(1 downto 0); -- estado da maquina de estados
    signal fetch_internal, decode_internal, execute_internal : std_logic; -- booleano para dizer em que etapa esta a maquina de estados
    
begin
    PC_reg: reg14bits
    port map
    (
        clk      => clk,
        rst      => rst,
        wr_en    => PC_reg_wr_en,
        data_in  => PC_reg_in,
        data_out => PC_reg_out
    );

    instruction_reg: reg14bits
    port map
    (
        clk      => clk,
        rst      => rst,
        wr_en    => instruction_reg_wr_en,
        data_in  => instruction_in,
        data_out => instruction_out_internal
    );
    
    state_machine1: state_machine
    port map
    (
        clk   => clk,
        rst   => rst,
        state => state_internal
    );

    -- estados da maquina de estados
    fetch_internal <= '1' when state_internal = "00" else '0'; -- se está em fetch precisa escrever no instruction register
    instruction_reg_wr_en <= fetch_internal;
    decode_internal <= '1' when state_internal = "01" else '0'; -- se está em decode precisa escrever no program counter
    PC_reg_wr_en <= decode_internal;
    execute <= '1' when state_internal = "10" else '0'; -- se está em execute ou nao

    -- dados da instrucao
    opcode <= instruction_out_internal(13 downto 10); -- opcode sao os 4 bits mais significativos da instrucao

    -- TODO: fiquei na duvida se pegava o jump pela ROM fazendo (13 downto 10), existe variavel global entre arquivos? arquivo de constantes talvez para graver opcodes
    jump_en <= '1' when opcode = "1111" else '0';

    -- se for jump, concatenar MSB do PC com o LSB da instrucao
    -- se nao somar 1
    PC_reg_in <= PC_reg_out(13 downto 10) & instruction_out_internal (9 downto 0) when jump_en = '1' else
    PC_reg_out + 1;--"0000000000001";

    -- repassando para output
    PC <= PC_reg_out;
    instruction_out <= instruction_out_internal;
    state <= state_internal;
    fetch <= fetch_internal;
    decode <= decode_internal;
    execute <= execute_internal;
end architecture a_uc;

uc_tb.vhd
library ieee;
use ieee.std_logic_1164.all;
use ieee.numeric_std.all;

entity uc_tb is
end;

architecture a_uc_tb of uc_tb is
    component uc is
        port
        (
            clk             : IN std_logic ;
            rst             : IN std_logic ;
            instruction_in  : IN unsigned (13 downto 0);
            instruction_out : OUT unsigned (13 downto 0);
            PC              : OUT unsigned (13 downto 0);
            fetch           : OUT std_logic ;
            decode          : OUT std_logic ;
            execute         : OUT std_logic ;
            state           : OUT unsigned (1 downto 0)
        );
    end component;
    
    constant period_time : time := 100 ns;
    signal finished : std_logic := '0';
    
    signal clk, rst: std_logic;
    signal instruction_in, instruction_out, PC : unsigned (13 downto 0);
    signal fetch, decode, execute: std_logic;
    signal state: unsigned (1 downto 0);

begin
    uut: uc
    port map
    (
        clk             => clk,
        rst             => rst,
        instruction_in  => instruction_in,
        instruction_out => instruction_out,
        PC              => PC,
        fetch           => fetch,
        decode          => decode,
        execute         => execute,
        state           => state
    );


    reset_global: process
    begin
        rst <= '1';
        wait for period_time*2;
        rst <= '0';
        wait;
    end process reset_global;
    
    sim_time_proc: process
    begin
        wait for 100 us;
        finished <= '1';
        wait;
    end process sim_time_proc;
    
    clk_proc: process
    begin
        while finished /= '1' loop
            clk <= '0';
            wait for period_time / 2;
            clk <= '1';
            wait for period_time / 2;
        end loop;
        wait;
    end process clk_proc;
    
    process
    begin
        -- resumo: program counter ira somar por 10 periodos
        -- depois ira fazer um jump para o endereco 3
        -- depois ira continuar incrementando 1 no program counter
        instruction_in <= "00000000000000"; -- NOP
        wait for period_time * 10;
        
        instruction_in <= "11110001110011"; -- JUMP
        wait for period_time * 2;
        
        instruction_in <= "00000000000000"; -- NOP
        wait for period_time * 10;

        instruction_in <= "11110000101010"; -- JUMP
        wait;
        
    end process;
    
end architecture a_uc_tb;

uc_tb.vcd
$date
  Wed May 18 22:52:46 2022
$end
$version
  GHDL v0
$end
$timescale
  1 fs
$end
$scope module standard $end
$upscope $end
$scope module std_logic_1164 $end
$upscope $end
$scope module numeric_std $end
$upscope $end
$scope module uc_tb $end
$var reg 1 ! finished $end
$var reg 1 " clk $end
$var reg 1 # rst $end
$var reg 14 $ instruction_in[13:0] $end
$var reg 14 % instruction_out[13:0] $end
$var reg 14 & pc[13:0] $end
$var reg 1 ' fetch $end
$var reg 1 ( decode $end
$var reg 1 ) execute $end
$var reg 2 * state[1:0] $end
$scope module uut $end
$var reg 1 + clk $end
$var reg 1 , rst $end
$var reg 14 - instruction_in[13:0] $end
$var reg 14 . instruction_out[13:0] $end
$var reg 14 / pc[13:0] $end
$var reg 1 0 fetch $end
$var reg 1 1 decode $end
$var reg 1 2 execute $end
$var reg 2 3 state[1:0] $end
$var reg 14 4 pc_reg_in[13:0] $end
$var reg 14 5 pc_reg_out[13:0] $end
$var reg 4 6 opcode[3:0] $end
$var reg 1 7 pc_reg_wr_en $end
$var reg 1 8 instruction_reg_wr_en $end
$var reg 1 9 jump_en $end
$var reg 14 : instruction_out_internal[13:0] $end
$var reg 2 ; state_internal[1:0] $end
$var reg 1 < fetch_internal $end
$var reg 1 = decode_internal $end
$var reg 1 > execute_internal $end
$scope module pc_reg $end
$var reg 1 ? clk $end
$var reg 1 @ rst $end
$var reg 1 A wr_en $end
$var reg 14 B data_in[13:0] $end
$var reg 14 C data_out[13:0] $end
$var reg 14 D reg[13:0] $end
$upscope $end
$scope module instruction_reg $end
$var reg 1 E clk $end
$var reg 1 F rst $end
$var reg 1 G wr_en $end
$var reg 14 H data_in[13:0] $end
$var reg 14 I data_out[13:0] $end
$var reg 14 J reg[13:0] $end
$upscope $end
$scope module state_machine1 $end
$var reg 1 K clk $end
$var reg 1 L rst $end
$var reg 2 M state[1:0] $end
$var reg 2 N internal_state[1:0] $end
$upscope $end
$upscope $end
$upscope $end
$enddefinitions $end
#0
0!
0"
1#
b00000000000000 $
b00000000000000 %
b00000000000000 &
1'
0(
U)
b00 *
0+
1,
b00000000000000 -
b00000000000000 .
b00000000000000 /
10
01
U2
b00 3
b00000000000001 4
b00000000000000 5
b0000 6
07
18
09
b00000000000000 :
b00 ;
1<
0=
U>
0?
1@
0A
b00000000000001 B
b00000000000000 C
b00000000000000 D
0E
1F
1G
b00000000000000 H
b00000000000000 I
b00000000000000 J
0K
1L
b00 M
b00 N
#50000000
1"
1+
1?
1E
1K
#100000000
0"
0+
0?
0E
0K
#150000000
1"
1+
1?
1E
1K
#200000000
0"
0#
0+
0,
0?
0@
0E
0F
0K
0L
#250000000
1"
0'
1(
b01 *
1+
00
11
U2
b01 3
17
08
b01 ;
0<
1=
1?
1A
1E
0G
1K
b01 M
b01 N
#300000000
0"
0+
0?
0E
0K
#350000000
1"
b00000000000001 &
0(
b10 *
1+
b00000000000001 /
01
U2
b10 3
b00000000000010 4
b00000000000001 5
07
b10 ;
0=
1?
0A
b00000000000010 B
b00000000000001 C
b00000000000001 D
1E
1K
b10 M
b10 N
#400000000
0"
0+
0?
0E
0K
#450000000
1"
1'
b00 *
1+
10
U2
b00 3
18
b00 ;
1<
1?
1E
1G
1K
b00 M
b00 N
#500000000
0"
0+
0?
0E
0K
#550000000
1"
0'
1(
b01 *
1+
00
11
U2
b01 3
17
08
b01 ;
0<
1=
1?
1A
1E
0G
1K
b01 M
b01 N
#600000000
0"
0+
0?
0E
0K
#650000000
1"
b00000000000010 &
0(
b10 *
1+
b00000000000010 /
01
U2
b10 3
b00000000000011 4
b00000000000010 5
07
b10 ;
0=
1?
0A
b00000000000011 B
b00000000000010 C
b00000000000010 D
1E
1K
b10 M
b10 N
#700000000
0"
0+
0?
0E
0K
#750000000
1"
1'
b00 *
1+
10
U2
b00 3
18
b00 ;
1<
1?
1E
1G
1K
b00 M
b00 N
#800000000
0"
0+
0?
0E
0K
#850000000
1"
0'
1(
b01 *
1+
00
11
U2
b01 3
17
08
b01 ;
0<
1=
1?
1A
1E
0G
1K
b01 M
b01 N
#900000000
0"
0+
0?
0E
0K
#950000000
1"
b00000000000011 &
0(
b10 *
1+
b00000000000011 /
01
U2
b10 3
b00000000000100 4
b00000000000011 5
07
b10 ;
0=
1?
0A
b00000000000100 B
b00000000000011 C
b00000000000011 D
1E
1K
b10 M
b10 N
#1000000000
0"
b11110001110011 $
0+
b11110001110011 -
0?
0E
b11110001110011 H
0K
#1050000000
1"
1'
b00 *
1+
10
U2
b00 3
18
b00 ;
1<
1?
1E
1G
1K
b00 M
b00 N
#1100000000
0"
0+
0?
0E
0K
#1150000000
1"
b11110001110011 %
0'
1(
b01 *
1+
b11110001110011 .
00
11
U2
b01 3
b00000001110011 4
b1111 6
17
08
19
b11110001110011 :
b01 ;
0<
1=
1?
1A
b00000001110011 B
1E
0G
b11110001110011 I
b11110001110011 J
1K
b01 M
b01 N
#1200000000
0"
b00000000000000 $
0+
b00000000000000 -
0?
0E
b00000000000000 H
0K
#1250000000
1"
b00000001110011 &
0(
b10 *
1+
b00000001110011 /
01
U2
b10 3
b00000001110011 5
07
b10 ;
0=
1?
0A
b00000001110011 C
b00000001110011 D
1E
1K
b10 M
b10 N
#1300000000
0"
0+
0?
0E
0K
#1350000000
1"
1'
b00 *
1+
10
U2
b00 3
18
b00 ;
1<
1?
1E
1G
1K
b00 M
b00 N
#1400000000
0"
0+
0?
0E
0K
#1450000000
1"
b00000000000000 %
0'
1(
b01 *
1+
b00000000000000 .
00
11
U2
b01 3
b00000001110100 4
b0000 6
17
08
09
b00000000000000 :
b01 ;
0<
1=
1?
1A
b00000001110100 B
1E
0G
b00000000000000 I
b00000000000000 J
1K
b01 M
b01 N
#1500000000
0"
0+
0?
0E
0K
#1550000000
1"
b00000001110100 &
0(
b10 *
1+
b00000001110100 /
01
U2
b10 3
b00000001110101 4
b00000001110100 5
07
b10 ;
0=
1?
0A
b00000001110101 B
b00000001110100 C
b00000001110100 D
1E
1K
b10 M
b10 N
#1600000000
0"
0+
0?
0E
0K
#1650000000
1"
1'
b00 *
1+
10
U2
b00 3
18
b00 ;
1<
1?
1E
1G
1K
b00 M
b00 N
#1700000000
0"
0+
0?
0E
0K
#1750000000
1"
0'
1(
b01 *
1+
00
11
U2
b01 3
17
08
b01 ;
0<
1=
1?
1A
1E
0G
1K
b01 M
b01 N
#1800000000
0"
0+
0?
0E
0K
#1850000000
1"
b00000001110101 &
0(
b10 *
1+
b00000001110101 /
01
U2
b10 3
b00000001110110 4
b00000001110101 5
07
b10 ;
0=
1?
0A
b00000001110110 B
b00000001110101 C
b00000001110101 D
1E
1K
b10 M
b10 N
#1900000000
0"
0+
0?
0E
0K
#1950000000
1"
1'
b00 *
1+
10
U2
b00 3
18
b00 ;
1<
1?
1E
1G
1K
b00 M
b00 N
#2000000000
0"
0+
0?
0E
0K
#2050000000
1"
0'
1(
b01 *
1+
00
11
U2
b01 3
17
08
b01 ;
0<
1=
1?
1A
1E
0G
1K
b01 M
b01 N
#2100000000
0"
0+
0?
0E
0K
#2150000000
1"
b00000001110110 &
0(
b10 *
1+
b00000001110110 /
01
U2
b10 3
b00000001110111 4
b00000001110110 5
07
b10 ;
0=
1?
0A
b00000001110111 B
b00000001110110 C
b00000001110110 D
1E
1K
b10 M
b10 N
#2200000000
0"
b11110000101010 $
0+
b11110000101010 -
0?
0E
b11110000101010 H
0K
#2250000000
1"
1'
b00 *
1+
10
U2
b00 3
18
b00 ;
1<
1?
1E
1G
1K
b00 M
b00 N
#2300000000
0"
0+
0?
0E
0K
#2350000000
1"
b11110000101010 %
0'
1(
b01 *
1+
b11110000101010 .
00
11
U2
b01 3
b00000000101010 4
b1111 6
17
08
19
b11110000101010 :
b01 ;
0<
1=
1?
1A
b00000000101010 B
1E
0G
b11110000101010 I
b11110000101010 J
1K
b01 M
b01 N
#2400000000
0"
0+
0?
0E
0K
#2450000000
1"
b00000000101010 &
0(
b10 *
1+
b00000000101010 /
01
U2
b10 3
b00000000101010 5
07
b10 ;
0=
1?
0A
b00000000101010 C
b00000000101010 D
1E
1K
b10 M
b10 N
#2500000000
0"
0+
0?
0E
0K
#2550000000
1"
1'
b00 *
1+
10
U2
b00 3
18
b00 ;
1<
1?
1E
1G
1K
b00 M
b00 N
#2600000000
0"
0+
0?
0E
0K
#2650000000
1"
0'
1(
b01 *
1+
00
11
U2
b01 3
17
08
b01 ;
0<
1=
1?
1A
1E
0G
1K
b01 M
b01 N
#2700000000
0"
0+
0?
0E
0K
#2750000000
1"
0(
b10 *
1+
01
U2
b10 3
07
b10 ;
0=
1?
0A
1E
1K
b10 M
b10 N
#2800000000
0"
0+
0?
0E
0K
#2850000000
1"
1'
b00 *
1+
10
U2
b00 3
18
b00 ;
1<
1?
1E
1G
1K
b00 M
b00 N
#2900000000
0"
0+
0?
0E
0K
#2950000000
1"
0'
1(
b01 *
1+
00
11
U2
b01 3
17
08
b01 ;
0<
1=
1?
1A
1E
0G
1K
b01 M
b01 N
#3000000000
0"
0+
0?
0E
0K
#3050000000
1"
0(
b10 *
1+
01
U2
b10 3
07
b10 ;
0=
1?
0A
1E
1K
b10 M
b10 N
#3100000000
0"
0+
0?
0E
0K
#3150000000
1"
1'
b00 *
1+
10
U2
b00 3
18
b00 ;
1<
1?
1E
1G
1K
b00 M
b00 N
#3200000000
0"
0+
0?
0E
0K
#3250000000
1"
0'
1(
b01 *
1+
00
11
U2
b01 3
17
08
b01 ;
0<
1=
1?
1A
1E
0G
1K
b01 M
b01 N
#3300000000
0"
0+
0?
0E
0K
#3350000000
1"
0(
b10 *
1+
01
U2
b10 3
07
b10 ;
0=
1?
0A
1E
1K
b10 M
b10 N
#3400000000
0"
0+
0?
0E
0K
#3450000000
1"
1'
b00 *
1+
10
U2
b00 3
18
b00 ;
1<
1?
1E
1G
1K
b00 M
b00 N
#3500000000
0"
0+
0?
0E
0K
#3550000000
1"
0'
1(
b01 *
1+
00
11
U2
b01 3
17
08
b01 ;
0<
1=
1?
1A
1E
0G
1K
b01 M
b01 N
#3600000000
0"
0+
0?
0E
0K
#3650000000
1"
0(
b10 *
1+
01
U2
b10 3
07
b10 ;
0=
1?
0A
1E
1K
b10 M
b10 N
#3700000000
0"
0+
0?
0E
0K
#3750000000
1"
1'
b00 *
1+
10
U2
b00 3
18
b00 ;
1<
1?
1E
1G
1K
b00 M
b00 N
#3800000000
0"
0+
0?
0E
0K
#3850000000
1"
0'
1(
b01 *
1+
00
11
U2
b01 3
17
08
b01 ;
0<
1=
1?
1A
1E
0G
1K
b01 M
b01 N
#3900000000
0"
0+
0?
0E
0K
#3950000000
1"
0(
b10 *
1+
01
U2
b10 3
07
b10 ;
0=
1?
0A
1E
1K
b10 M
b10 N
#4000000000
0"
0+
0?
0E
0K
#4050000000
1"
1'
b00 *
1+
10
U2
b00 3
18
b00 ;
1<
1?
1E
1G
1K
b00 M
b00 N
#4100000000
0"
0+
0?
0E
0K
#4150000000
1"
0'
1(
b01 *
1+
00
11
U2
b01 3
17
08
b01 ;
0<
1=
1?
1A
1E
0G
1K
b01 M
b01 N
#4200000000
0"
0+
0?
0E
0K
#4250000000
1"
0(
b10 *
1+
01
U2
b10 3
07
b10 ;
0=
1?
0A
1E
1K
b10 M
b10 N
#4300000000
0"
0+
0?
0E
0K
#4350000000
1"
1'
b00 *
1+
10
U2
b00 3
18
b00 ;
1<
1?
1E
1G
1K
b00 M
b00 N
#4400000000
0"
0+
0?
0E
0K
#4450000000
1"
0'
1(
b01 *
1+
00
11
U2
b01 3
17
08
b01 ;
0<
1=
1?
1A
1E
0G
1K
b01 M
b01 N
#4500000000
0"
0+
0?
0E
0K
#4550000000
1"
0(
b10 *
1+
01
U2
b10 3
07
b10 ;
0=
1?
0A
1E
1K
b10 M
b10 N
#4600000000
0"
0+
0?
0E
0K
#4650000000
1"
1'
b00 *
1+
10
U2
b00 3
18
b00 ;
1<
1?
1E
1G
1K
b00 M
b00 N
#4700000000
0"
0+
0?
0E
0K
#4750000000
1"
0'
1(
b01 *
1+
00
11
U2
b01 3
17
08
b01 ;
0<
1=
1?
1A
1E
0G
1K
b01 M
b01 N
#4800000000
0"
0+
0?
0E
0K
#4850000000
1"
0(
b10 *
1+
01
U2
b10 3
07
b10 ;
0=
1?
0A
1E
1K
b10 M
b10 N
#4900000000
0"
0+
0?
0E
0K
#4950000000
1"
1'
b00 *
1+
10
U2
b00 3
18
b00 ;
1<
1?
1E
1G
1K
b00 M
b00 N
#5000000000
0"
0+
0?
0E
0K
#5050000000
1"
0'
1(
b01 *
1+
00
11
U2
b01 3
17
08
b01 ;
0<
1=
1?
1A
1E
0G
1K
b01 M
b01 N
#5100000000
0"
0+
0?
0E
0K
#5150000000
1"
0(
b10 *
1+
01
U2
b10 3
07
b10 ;
0=
1?
0A
1E
1K
b10 M
b10 N
#5200000000
0"
0+
0?
0E
0K
#5250000000
1"
1'
b00 *
1+
10
U2
b00 3
18
b00 ;
1<
1?
1E
1G
1K
b00 M
b00 N
#5300000000
0"
0+
0?
0E
0K
#5350000000
1"
0'
1(
b01 *
1+
00
11
U2
b01 3
17
08
b01 ;
0<
1=
1?
1A
1E
0G
1K
b01 M
b01 N
#5400000000
0"
0+
0?
0E
0K
#5450000000
1"
0(
b10 *
1+
01
U2
b10 3
07
b10 ;
0=
1?
0A
1E
1K
b10 M
b10 N
#5500000000
0"
0+
0?
0E
0K
#5550000000
1"
1'
b00 *
1+
10
U2
b00 3
18
b00 ;
1<
1?
1E
1G
1K
b00 M
b00 N
#5600000000
0"
0+
0?
0E
0K
#5650000000
1"
0'
1(
b01 *
1+
00
11
U2
b01 3
17
08
b01 ;
0<
1=
1?
1A
1E
0G
1K
b01 M
b01 N
#5700000000
0"
0+
0?
0E
0K
#5750000000
1"
0(
b10 *
1+
01
U2
b10 3
07
b10 ;
0=
1?
0A
1E
1K
b10 M
b10 N
#5800000000
0"
0+
0?
0E
0K
#5850000000
1"
1'
b00 *
1+
10
U2
b00 3
18
b00 ;
1<
1?
1E
1G
1K
b00 M
b00 N
#5900000000
0"
0+
0?
0E
0K
#5950000000
1"
0'
1(
b01 *
1+
00
11
U2
b01 3
17
08
b01 ;
0<
1=
1?
1A
1E
0G
1K
b01 M
b01 N
#6000000000
0"
0+
0?
0E
0K
#6050000000
1"
0(
b10 *
1+
01
U2
b10 3
07
b10 ;
0=
1?
0A
1E
1K
b10 M
b10 N
#6100000000
0"
0+
0?
0E
0K
#6150000000
1"
1'
b00 *
1+
10
U2
b00 3
18
b00 ;
1<
1?
1E
1G
1K
b00 M
b00 N
#6200000000
0"
0+
0?
0E
0K
#6250000000
1"
0'
1(
b01 *
1+
00
11
U2
b01 3
17
08
b01 ;
0<
1=
1?
1A
1E
0G
1K
b01 M
b01 N
#6300000000
0"
0+
0?
0E
0K
#6350000000
1"
0(
b10 *
1+
01
U2
b10 3
07
b10 ;
0=
1?
0A
1E
1K
b10 M
b10 N
#6400000000
0"
0+
0?
0E
0K
#6450000000
1"
1'
b00 *
1+
10
U2
b00 3
18
b00 ;
1<
1?
1E
1G
1K
b00 M
b00 N
#6500000000
0"
0+
0?
0E
0K
#6550000000
1"
0'
1(
b01 *
1+
00
11
U2
b01 3
17
08
b01 ;
0<
1=
1?
1A
1E
0G
1K
b01 M
b01 N
#6600000000
0"
0+
0?
0E
0K
#6650000000
1"
0(
b10 *
1+
01
U2
b10 3
07
b10 ;
0=
1?
0A
1E
1K
b10 M
b10 N
#6700000000
0"
0+
0?
0E
0K
#6750000000
1"
1'
b00 *
1+
10
U2
b00 3
18
b00 ;
1<
1?
1E
1G
1K
b00 M
b00 N
#6800000000
0"
0+
0?
0E
0K
#6850000000
1"
0'
1(
b01 *
1+
00
11
U2
b01 3
17
08
b01 ;
0<
1=
1?
1A
1E
0G
1K
b01 M
b01 N
#6900000000
0"
0+
0?
0E
0K
#6950000000
1"
0(
b10 *
1+
01
U2
b10 3
07
b10 ;
0=
1?
0A
1E
1K
b10 M
b10 N
#7000000000
0"
0+
0?
0E
0K
#7050000000
1"
1'
b00 *
1+
10
U2
b00 3
18
b00 ;
1<
1?
1E
1G
1K
b00 M
b00 N
#7100000000
0"
0+
0?
0E
0K
#7150000000
1"
0'
1(
b01 *
1+
00
11
U2
b01 3
17
08
b01 ;
0<
1=
1?
1A
1E
0G
1K
b01 M
b01 N
#7200000000
0"
0+
0?
0E
0K
#7250000000
1"
0(
b10 *
1+
01
U2
b10 3
07
b10 ;
0=
1?
0A
1E
1K
b10 M
b10 N
#7300000000
0"
0+
0?
0E
0K
#7350000000
1"
1'
b00 *
1+
10
U2
b00 3
18
b00 ;
1<
1?
1E
1G
1K
b00 M
b00 N
#7400000000
0"
0+
0?
0E
0K
#7450000000
1"
0'
1(
b01 *
1+
00
11
U2
b01 3
17
08
b01 ;
0<
1=
1?
1A
1E
0G
1K
b01 M
b01 N
#7500000000
0"
0+
0?
0E
0K
#7550000000
1"
0(
b10 *
1+
01
U2
b10 3
07
b10 ;
0=
1?
0A
1E
1K
b10 M
b10 N
#7600000000
0"
0+
0?
0E
0K
#7650000000
1"
1'
b00 *
1+
10
U2
b00 3
18
b00 ;
1<
1?
1E
1G
1K
b00 M
b00 N
#7700000000
0"
0+
0?
0E
0K
#7750000000
1"
0'
1(
b01 *
1+
00
11
U2
b01 3
17
08
b01 ;
0<
1=
1?
1A
1E
0G
1K
b01 M
b01 N
#7800000000
0"
0+
0?
0E
0K
#7850000000
1"
0(
b10 *
1+
01
U2
b10 3
07
b10 ;
0=
1?
0A
1E
1K
b10 M
b10 N
#7900000000
0"
0+
0?
0E
0K
#7950000000
1"
1'
b00 *
1+
10
U2
b00 3
18
b00 ;
1<
1?
1E
1G
1K
b00 M
b00 N
#8000000000
0"
0+
0?
0E
0K
#8050000000
1"
0'
1(
b01 *
1+
00
11
U2
b01 3
17
08
b01 ;
0<
1=
1?
1A
1E
0G
1K
b01 M
b01 N
#8100000000
0"
0+
0?
0E
0K
#8150000000
1"
0(
b10 *
1+
01
U2
b10 3
07
b10 ;
0=
1?
0A
1E
1K
b10 M
b10 N
#8200000000
0"
0+
0?
0E
0K
#8250000000
1"
1'
b00 *
1+
10
U2
b00 3
18
b00 ;
1<
1?
1E
1G
1K
b00 M
b00 N
#8300000000
0"
0+
0?
0E
0K
#8350000000
1"
0'
1(
b01 *
1+
00
11
U2
b01 3
17
08
b01 ;
0<
1=
1?
1A
1E
0G
1K
b01 M
b01 N
#8400000000
0"
0+
0?
0E
0K
#8450000000
1"
0(
b10 *
1+
01
U2
b10 3
07
b10 ;
0=
1?
0A
1E
1K
b10 M
b10 N
#8500000000
0"
0+
0?
0E
0K
#8550000000
1"
1'
b00 *
1+
10
U2
b00 3
18
b00 ;
1<
1?
1E
1G
1K
b00 M
b00 N
#8600000000
0"
0+
0?
0E
0K
#8650000000
1"
0'
1(
b01 *
1+
00
11
U2
b01 3
17
08
b01 ;
0<
1=
1?
1A
1E
0G
1K
b01 M
b01 N
#8700000000
0"
0+
0?
0E
0K
#8750000000
1"
0(
b10 *
1+
01
U2
b10 3
07
b10 ;
0=
1?
0A
1E
1K
b10 M
b10 N
#8800000000
0"
0+
0?
0E
0K
#8850000000
1"
1'
b00 *
1+
10
U2
b00 3
18
b00 ;
1<
1?
1E
1G
1K
b00 M
b00 N
#8900000000
0"
0+
0?
0E
0K
#8950000000
1"
0'
1(
b01 *
1+
00
11
U2
b01 3
17
08
b01 ;
0<
1=
1?
1A
1E
0G
1K
b01 M
b01 N
#9000000000
0"
0+
0?
0E
0K
#9050000000
1"
0(
b10 *
1+
01
U2
b10 3
07
b10 ;
0=
1?
0A
1E
1K
b10 M
b10 N
#9100000000
0"
0+
0?
0E
0K
#9150000000
1"
1'
b00 *
1+
10
U2
b00 3
18
b00 ;
1<
1?
1E
1G
1K
b00 M
b00 N
#9200000000
0"
0+
0?
0E
0K
#9250000000
1"
0'
1(
b01 *
1+
00
11
U2
b01 3
17
08
b01 ;
0<
1=
1?
1A
1E
0G
1K
b01 M
b01 N
#9300000000
0"
0+
0?
0E
0K
#9350000000
1"
0(
b10 *
1+
01
U2
b10 3
07
b10 ;
0=
1?
0A
1E
1K
b10 M
b10 N
#9400000000
0"
0+
0?
0E
0K
#9450000000
1"
1'
b00 *
1+
10
U2
b00 3
18
b00 ;
1<
1?
1E
1G
1K
b00 M
b00 N
#9500000000
0"
0+
0?
0E
0K
#9550000000
1"
0'
1(
b01 *
1+
00
11
U2
b01 3
17
08
b01 ;
0<
1=
1?
1A
1E
0G
1K
b01 M
b01 N
#9600000000
0"
0+
0?
0E
0K
#9650000000
1"
0(
b10 *
1+
01
U2
b10 3
07
b10 ;
0=
1?
0A
1E
1K
b10 M
b10 N
#9700000000
0"
0+
0?
0E
0K
#9750000000
1"
1'
b00 *
1+
10
U2
b00 3
18
b00 ;
1<
1?
1E
1G
1K
b00 M
b00 N
#9800000000
0"
0+
0?
0E
0K
#9850000000
1"
0'
1(
b01 *
1+
00
11
U2
b01 3
17
08
b01 ;
0<
1=
1?
1A
1E
0G
1K
b01 M
b01 N
#9900000000
0"
0+
0?
0E
0K
#9950000000
1"
0(
b10 *
1+
01
U2
b10 3
07
b10 ;
0=
1?
0A
1E
1K
b10 M
b10 N
#10000000000
0"
0+
0?
0E
0K
#10050000000
1"
1'
b00 *
1+
10
U2
b00 3
18
b00 ;
1<
1?
1E
1G
1K
b00 M
b00 N
#10100000000
0"
0+
0?
0E
0K
#10150000000
1"
0'
1(
b01 *
1+
00
11
U2
b01 3
17
08
b01 ;
0<
1=
1?
1A
1E
0G
1K
b01 M
b01 N
#10200000000
0"
0+
0?
0E
0K
#10250000000
1"
0(
b10 *
1+
01
U2
b10 3
07
b10 ;
0=
1?
0A
1E
1K
b10 M
b10 N
#10300000000
0"
0+
0?
0E
0K
#10350000000
1"
1'
b00 *
1+
10
U2
b00 3
18
b00 ;
1<
1?
1E
1G
1K
b00 M
b00 N
#10400000000
0"
0+
0?
0E
0K
#10450000000
1"
0'
1(
b01 *
1+
00
11
U2
b01 3
17
08
b01 ;
0<
1=
1?
1A
1E
0G
1K
b01 M
b01 N
#10500000000
0"
0+
0?
0E
0K
#10550000000
1"
0(
b10 *
1+
01
U2
b10 3
07
b10 ;
0=
1?
0A
1E
1K
b10 M
b10 N
#10600000000
0"
0+
0?
0E
0K
#10650000000
1"
1'
b00 *
1+
10
U2
b00 3
18
b00 ;
1<
1?
1E
1G
1K
b00 M
b00 N
#10700000000
0"
0+
0?
0E
0K
#10750000000
1"
0'
1(
b01 *
1+
00
11
U2
b01 3
17
08
b01 ;
0<
1=
1?
1A
1E
0G
1K
b01 M
b01 N
#10800000000
0"
0+
0?
0E
0K
#10850000000
1"
0(
b10 *
1+
01
U2
b10 3
07
b10 ;
0=
1?
0A
1E
1K
b10 M
b10 N
#10900000000
0"
0+
0?
0E
0K
#10950000000
1"
1'
b00 *
1+
10
U2
b00 3
18
b00 ;
1<
1?
1E
1G
1K
b00 M
b00 N
#11000000000
0"
0+
0?
0E
0K
#11050000000
1"
0'
1(
b01 *
1+
00
11
U2
b01 3
17
08
b01 ;
0<
1=
1?
1A
1E
0G
1K
b01 M
b01 N
#11100000000
0"
0+
0?
0E
0K
#11150000000
1"
0(
b10 *
1+
01
U2
b10 3
07
b10 ;
0=
1?
0A
1E
1K
b10 M
b10 N
#11200000000
0"
0+
0?
0E
0K
#11250000000
1"
1'
b00 *
1+
10
U2
b00 3
18
b00 ;
1<
1?
1E
1G
1K
b00 M
b00 N
#11300000000
0"
0+
0?
0E
0K
#11350000000
1"
0'
1(
b01 *
1+
00
11
U2
b01 3
17
08
b01 ;
0<
1=
1?
1A
1E
0G
1K
b01 M
b01 N
#11400000000
0"
0+
0?
0E
0K
