rom.vhd
library IEEE;
use IEEE.std_logic_1164.all;
use IEEE.numeric_std.all;

entity rom is
    port(
        clk: IN STD_LOGIC;
        address: IN unsigned(6 downto 0);
        data: OUT unsigned(13 downto 0)
    );
end entity rom;

architecture a_rom of rom is
    type mem is array (0 to 127) of unsigned(13 downto 0);
    constant rom_content : mem := (
        0 => B"0000_0000000000", -- NOP
        1 => B"0001_0_001_011_000", -- ADD (Registrador) (Registrador)
        2 => B"0001_1_000_000000", -- ADD (Registrador) constante
        3 => B"0010_0_000_000_000", -- SUB (Registrador) (Registrador)
        4 => B"0010_1_000_000000", -- SUB (Registrador) constante
        5 => B"0011_001_011_0000", -- MOV (Registrador) (Registrador)
        6 => B"0000_0000000000", -- NOP
        7 => B"0000_0000000000", -- NOP
        8 => B"0000_0000000000", -- NOP
        9 => B"0000_0000000000", -- NOP
        10 => B"1111_0000000000", -- JA ADDR
        others => (others => '0')
    );
begin
    process(clk)
    begin
        if(rising_edge(clk)) then
            data <= rom_content(to_integer(address));
        end if;
    end process;
end architecture;

state_machine.vhd
library ieee;
use ieee.std_logic_1164.all;
use ieee.numeric_std.all;

entity state_machine is
    port(
        clk : in std_logic;
        rst : in std_logic;
        state : out std_logic
    );
end entity;

architecture a_state_machine of state_machine is
    signal internal_state: std_logic;
begin
    process(clk,rst)
    begin
        if rst='1' then
            internal_state <= '0';
        elsif rising_edge(clk) then
            internal_state <= not internal_state;
        end if;
    end process;

    state <= internal_state;
end architecture;

reg16bits.vhd
library ieee;
use ieee.std_logic_1164.all;
use ieee.numeric_std.all;

entity reg16bits is
    port(
        clk : in std_logic;
        rst : in std_logic;
        wr_en : in std_logic;
        data_in : in unsigned(15 downto 0);
        data_out : out unsigned(15 downto 0)
    );
end entity;

architecture a_reg16bits of reg16bits is
    signal reg: unsigned(15 downto 0);
begin
    process(clk,rst,wr_en)
    begin
        if rst='1' then
            reg <= "0000000000000000";
        elsif wr_en='1' then
            if rising_edge(clk) then
                reg <= data_in;
            end if;
        end if;
    end process;

    data_out <= reg;
end architecture;

uc.vhd
library ieee;
use ieee.std_logic_1164.all;
use ieee.numeric_std.all;

entity uc is
    port(
        clk : IN  std_logic;
        rst : IN  std_logic;
        instruction : IN unsigned (13 downto 0);
        PC: OUT unsigned(15 downto 0)
    );
end entity uc;

architecture a_uc of uc is
    component reg16bits is
        port
        (
            clk      : IN std_logic ;
            rst      : IN std_logic ;
            wr_en    : IN std_logic ;
            data_in  : IN unsigned (15 downto 0);
            data_out : OUT unsigned (15 downto 0)
        );
    end component;
    
    component state_machine is
        port
        (
            clk : in std_logic;
            rst : in std_logic;
            state : out std_logic
        );
    end component state_machine;

    component rom is
        port
        (
            clk     : IN STD_LOGIC ;
            address : IN unsigned (6 downto 0);
            data    : OUT unsigned (13 downto 0)
        );
    end component;
    
    signal PC_in, PC_out : unsigned(15 downto 0);
    signal opcode : unsigned(3 downto 0);
    signal address : unsigned(6 downto 0);
    signal data : unsigned(13 downto 0);
    signal state, PC_wr_en, jump_en : std_logic;
    
begin
    PC_reg: reg16bits
    port map
    (
        clk      => clk,
        rst      => rst,
        wr_en    => '1',
        data_in  => PC_in,
        data_out => PC_out
    );
    
    stateMachine: state_machine
    port map
    (
        clk   => clk,
        rst   => rst,
        state => state
    );
    
    uc_rom : rom
    port map
    (
        clk     => clk,
        address => PC_out(6 downto 0),
        data    => data 
    );


    PC_wr_en <= state;
    
    opcode <= instruction(13 downto 10);

    jump_en <= '1' when opcode = "1111" else
    '0';
    
    PC_in <= PC_out(15 downto 11) & instruction (10 downto 0) when jump_en = '1' else
    PC_out + "000000000000001";
    
    PC <= PC_in;
    
end architecture a_uc;

uc_tb.vhd
library ieee;
use ieee.std_logic_1164.all;
use ieee.numeric_std.all;

entity uc_tb is
end;

architecture a_uc_tb of uc_tb is
    component uc is
        port
        (
            clk : IN  std_logic;
            rst : IN  std_logic;
            instruction : IN unsigned (13 downto 0);
            PC: OUT unsigned(15 downto 0)
        );
    end component;
    
    constant period_time : time := 100 ns;
    signal finished : std_logic := '0';
    
    signal clk, rst: std_logic;
    signal instruction : unsigned (13 downto 0);
    signal PC : unsigned(15 downto 0);
    
begin
    uut : uc
    port map
    (
        clk         => clk,
        rst         => rst,
        instruction => instruction,
        PC          => PC
    );

    reset_global: process
    begin
        rst <= '1';
        wait for period_time*2;
        rst <= '0';
        wait;
    end process reset_global;
    
    sim_time_proc: process
    begin
        wait for 100 us;
        finished <= '1';
        wait;
    end process sim_time_proc;
    
    clk_proc: process
    begin
        while finished /= '1' loop
            clk <= '0';
            wait for period_time / 2;
            clk <= '1';
            wait for period_time / 2;
        end loop;
        wait;
    end process clk_proc;
    
    process
    begin
        
        instruction <= "00000000000000";
        wait for period_time * 22;
        
        instruction <= "00000000101111";
        wait for period_time * 2;
        
        instruction <= "00000000000000";
        wait;
        
    end process;
    
end architecture a_uc_tb;

uc_tb.vcd
$date
  Wed May  4 20:37:20 2022
$end
$version
  GHDL v0
$end
$timescale
  1 fs
$end
$scope module standard $end
$upscope $end
$scope module textio $end
$upscope $end
$scope module std_logic_1164 $end
$upscope $end
$scope module numeric_std $end
$upscope $end
$scope module uc_tb $end
$var reg 1 ! finished $end
$var reg 1 " clk $end
$var reg 1 # rst $end
$var reg 14 $ instruction[13:0] $end
$var reg 16 % pc[15:0] $end
$scope module uut $end
$var reg 1 & clk $end
$var reg 1 ' rst $end
$var reg 14 ( instruction[13:0] $end
$var reg 16 ) pc[15:0] $end
$var reg 16 * pc_in[15:0] $end
$var reg 16 + pc_out[15:0] $end
$var reg 4 , opcode[3:0] $end
$var reg 7 - address[6:0] $end
$var reg 14 . data[13:0] $end
$var reg 1 / state $end
$var reg 1 0 pc_wr_en $end
$var reg 1 1 jump_en $end
$scope module pc_reg $end
$var reg 1 2 clk $end
$var reg 1 3 rst $end
$var reg 1 4 wr_en $end
$var reg 16 5 data_in[15:0] $end
$var reg 16 6 data_out[15:0] $end
$var reg 16 7 reg[15:0] $end
$upscope $end
$scope module statemachine $end
$var reg 1 8 clk $end
$var reg 1 9 rst $end
$var reg 1 : state $end
$var reg 1 ; internal_state $end
$upscope $end
$scope module uc_rom $end
$var reg 1 < clk $end
$var reg 7 = address[6:0] $end
$var reg 14 > data[13:0] $end
$upscope $end
$upscope $end
$upscope $end
$enddefinitions $end
#0
0!
0"
1#
b00000000000000 $
b0000000000000001 %
0&
1'
b00000000000000 (
b0000000000000001 )
b0000000000000001 *
b0000000000000000 +
b0000 ,
bUUUUUUU -
bUUUUUUUUUUUUUU .
0/
00
01
02
13
14
b0000000000000001 5
b0000000000000000 6
b0000000000000000 7
08
19
0:
0;
0<
b0000000 =
bUUUUUUUUUUUUUU >
#50000000
1"
1&
b00000000000000 .
12
18
1<
b00000000000000 >
#100000000
0"
0&
02
08
0<
#150000000
1"
1&
12
18
1<
#200000000
0"
0#
0&
0'
02
03
08
09
0<
#250000000
1"
b0000000000000010 %
1&
b0000000000000010 )
b0000000000000010 *
b0000000000000001 +
1/
10
12
b0000000000000010 5
b0000000000000001 6
b0000000000000001 7
18
1:
1;
1<
b0000001 =
#300000000
0"
0&
02
08
0<
#350000000
1"
b0000000000000011 %
1&
b0000000000000011 )
b0000000000000011 *
b0000000000000010 +
b00000000000001 .
0/
00
12
b0000000000000011 5
b0000000000000010 6
b0000000000000010 7
18
0:
0;
1<
b0000010 =
b00000000000001 >
#400000000
0"
0&
02
08
0<
#450000000
1"
b0000000000000100 %
1&
b0000000000000100 )
b0000000000000100 *
b0000000000000011 +
b00000000000010 .
1/
10
12
b0000000000000100 5
b0000000000000011 6
b0000000000000011 7
18
1:
1;
1<
b0000011 =
b00000000000010 >
#500000000
0"
0&
02
08
0<
#550000000
1"
b0000000000000101 %
1&
b0000000000000101 )
b0000000000000101 *
b0000000000000100 +
b00000000000100 .
0/
00
12
b0000000000000101 5
b0000000000000100 6
b0000000000000100 7
18
0:
0;
1<
b0000100 =
b00000000000100 >
#600000000
0"
0&
02
08
0<
#650000000
1"
b0000000000000110 %
1&
b0000000000000110 )
b0000000000000110 *
b0000000000000101 +
b00000000001000 .
1/
10
12
b0000000000000110 5
b0000000000000101 6
b0000000000000101 7
18
1:
1;
1<
b0000101 =
b00000000001000 >
#700000000
0"
0&
02
08
0<
#750000000
1"
b0000000000000111 %
1&
b0000000000000111 )
b0000000000000111 *
b0000000000000110 +
b00000000010000 .
0/
00
12
b0000000000000111 5
b0000000000000110 6
b0000000000000110 7
18
0:
0;
1<
b0000110 =
b00000000010000 >
#800000000
0"
0&
02
08
0<
#850000000
1"
b0000000000001000 %
1&
b0000000000001000 )
b0000000000001000 *
b0000000000000111 +
b00000000100000 .
1/
10
12
b0000000000001000 5
b0000000000000111 6
b0000000000000111 7
18
1:
1;
1<
b0000111 =
b00000000100000 >
#900000000
0"
0&
02
08
0<
#950000000
1"
b0000000000001001 %
1&
b0000000000001001 )
b0000000000001001 *
b0000000000001000 +
b00000001000000 .
0/
00
12
b0000000000001001 5
b0000000000001000 6
b0000000000001000 7
18
0:
0;
1<
b0001000 =
b00000001000000 >
#1000000000
0"
0&
02
08
0<
#1050000000
1"
b0000000000001010 %
1&
b0000000000001010 )
b0000000000001010 *
b0000000000001001 +
b00000010000000 .
1/
10
12
b0000000000001010 5
b0000000000001001 6
b0000000000001001 7
18
1:
1;
1<
b0001001 =
b00000010000000 >
#1100000000
0"
0&
02
08
0<
#1150000000
1"
b0000000000001011 %
1&
b0000000000001011 )
b0000000000001011 *
b0000000000001010 +
b00000100000000 .
0/
00
12
b0000000000001011 5
b0000000000001010 6
b0000000000001010 7
18
0:
0;
1<
b0001010 =
b00000100000000 >
#1200000000
0"
0&
02
08
0<
#1250000000
1"
b0000000000001100 %
1&
b0000000000001100 )
b0000000000001100 *
b0000000000001011 +
1/
10
12
b0000000000001100 5
b0000000000001011 6
b0000000000001011 7
18
1:
1;
1<
b0001011 =
#1300000000
0"
0&
02
08
0<
#1350000000
1"
b0000000000001101 %
1&
b0000000000001101 )
b0000000000001101 *
b0000000000001100 +
b00000000000000 .
0/
00
12
b0000000000001101 5
b0000000000001100 6
b0000000000001100 7
18
0:
0;
1<
b0001100 =
b00000000000000 >
#1400000000
0"
0&
02
08
0<
#1450000000
1"
b0000000000001110 %
1&
b0000000000001110 )
b0000000000001110 *
b0000000000001101 +
1/
10
12
b0000000000001110 5
b0000000000001101 6
b0000000000001101 7
18
1:
1;
1<
b0001101 =
#1500000000
0"
0&
02
08
0<
#1550000000
1"
b0000000000001111 %
1&
b0000000000001111 )
b0000000000001111 *
b0000000000001110 +
0/
00
12
b0000000000001111 5
b0000000000001110 6
b0000000000001110 7
18
0:
0;
1<
b0001110 =
#1600000000
0"
0&
02
08
0<
#1650000000
1"
b0000000000010000 %
1&
b0000000000010000 )
b0000000000010000 *
b0000000000001111 +
1/
10
12
b0000000000010000 5
b0000000000001111 6
b0000000000001111 7
18
1:
1;
1<
b0001111 =
#1700000000
0"
0&
02
08
0<
#1750000000
1"
b0000000000010001 %
1&
b0000000000010001 )
b0000000000010001 *
b0000000000010000 +
0/
00
12
b0000000000010001 5
b0000000000010000 6
b0000000000010000 7
18
0:
0;
1<
b0010000 =
#1800000000
0"
0&
02
08
0<
#1850000000
1"
b0000000000010010 %
1&
b0000000000010010 )
b0000000000010010 *
b0000000000010001 +
1/
10
12
b0000000000010010 5
b0000000000010001 6
b0000000000010001 7
18
1:
1;
1<
b0010001 =
#1900000000
0"
0&
02
08
0<
#1950000000
1"
b0000000000010011 %
1&
b0000000000010011 )
b0000000000010011 *
b0000000000010010 +
0/
00
12
b0000000000010011 5
b0000000000010010 6
b0000000000010010 7
18
0:
0;
1<
b0010010 =
#2000000000
0"
0&
02
08
0<
#2050000000
1"
b0000000000010100 %
1&
b0000000000010100 )
b0000000000010100 *
b0000000000010011 +
1/
10
12
b0000000000010100 5
b0000000000010011 6
b0000000000010011 7
18
1:
1;
1<
b0010011 =
#2100000000
0"
0&
02
08
0<
#2150000000
1"
b0000000000010101 %
1&
b0000000000010101 )
b0000000000010101 *
b0000000000010100 +
0/
00
12
b0000000000010101 5
b0000000000010100 6
b0000000000010100 7
18
0:
0;
1<
b0010100 =
#2200000000
0"
b00000000101111 $
0&
b00000000101111 (
02
08
0<
#2250000000
1"
b0000000000010110 %
1&
b0000000000010110 )
b0000000000010110 *
b0000000000010101 +
1/
10
12
b0000000000010110 5
b0000000000010101 6
b0000000000010101 7
18
1:
1;
1<
b0010101 =
#2300000000
0"
0&
02
08
0<
#2350000000
1"
b0000000000010111 %
1&
b0000000000010111 )
b0000000000010111 *
b0000000000010110 +
0/
00
12
b0000000000010111 5
b0000000000010110 6
b0000000000010110 7
18
0:
0;
1<
b0010110 =
#2400000000
0"
b00000000000000 $
0&
b00000000000000 (
02
08
0<
#2450000000
1"
b0000000000011000 %
1&
b0000000000011000 )
b0000000000011000 *
b0000000000010111 +
1/
10
12
b0000000000011000 5
b0000000000010111 6
b0000000000010111 7
18
1:
1;
1<
b0010111 =
#2500000000
0"
0&
02
08
0<
#2550000000
1"
b0000000000011001 %
1&
b0000000000011001 )
b0000000000011001 *
b0000000000011000 +
0/
00
12
b0000000000011001 5
b0000000000011000 6
b0000000000011000 7
18
0:
0;
1<
b0011000 =
#2600000000
0"
0&
02
08
0<
#2650000000
1"
b0000000000011010 %
1&
b0000000000011010 )
b0000000000011010 *
b0000000000011001 +
1/
10
12
b0000000000011010 5
b0000000000011001 6
b0000000000011001 7
18
1:
1;
1<
b0011001 =
#2700000000
0"
0&
02
08
0<
#2750000000
1"
b0000000000011011 %
1&
b0000000000011011 )
b0000000000011011 *
b0000000000011010 +
0/
00
12
b0000000000011011 5
b0000000000011010 6
b0000000000011010 7
18
0:
0;
1<
b0011010 =
#2800000000
0"
0&
02
08
0<
#2850000000
1"
b0000000000011100 %
1&
b0000000000011100 )
b0000000000011100 *
b0000000000011011 +
1/
10
12
b0000000000011100 5
b0000000000011011 6
b0000000000011011 7
18
1:
1;
1<
b0011011 =
#2900000000
0"
0&
02
08
0<
#2950000000
1"
b0000000000011101 %
1&
b0000000000011101 )
b0000000000011101 *
b0000000000011100 +
0/
00
12
b0000000000011101 5
b0000000000011100 6
b0000000000011100 7
18
0:
0;
1<
b0011100 =
#3000000000
0"
0&
02
08
0<
#3050000000
1"
b0000000000011110 %
1&
b0000000000011110 )
b0000000000011110 *
b0000000000011101 +
1/
10
12
b0000000000011110 5
b0000000000011101 6
b0000000000011101 7
18
1:
1;
1<
b0011101 =
#3100000000
0"
0&
02
08
0<
#3150000000
1"
b0000000000011111 %
1&
b0000000000011111 )
b0000000000011111 *
b0000000000011110 +
0/
00
12
b0000000000011111 5
b0000000000011110 6
b0000000000011110 7
18
0:
0;
1<
b0011110 =
#3200000000
0"
0&
02
08
0<
#3250000000
1"
b0000000000100000 %
1&
b0000000000100000 )
b0000000000100000 *
b0000000000011111 +
1/
10
12
b0000000000100000 5
b0000000000011111 6
b0000000000011111 7
18
1:
1;
1<
b0011111 =
#3300000000
0"
0&
02
08
0<
#3350000000
1"
b0000000000100001 %
1&
b0000000000100001 )
b0000000000100001 *
b0000000000100000 +
0/
00
12
b0000000000100001 5
b0000000000100000 6
b0000000000100000 7
18
0:
0;
1<
b0100000 =
#3400000000
0"
0&
02
08
0<
#3450000000
1"
b0000000000100010 %
1&
b0000000000100010 )
b0000000000100010 *
b0000000000100001 +
1/
10
12
b0000000000100010 5
b0000000000100001 6
b0000000000100001 7
18
1:
1;
1<
b0100001 =
#3500000000
0"
0&
02
08
0<
#3550000000
1"
b0000000000100011 %
1&
b0000000000100011 )
b0000000000100011 *
b0000000000100010 +
0/
00
12
b0000000000100011 5
b0000000000100010 6
b0000000000100010 7
18
0:
0;
1<
b0100010 =
#3600000000
0"
0&
02
08
0<
#3650000000
1"
b0000000000100100 %
1&
b0000000000100100 )
b0000000000100100 *
b0000000000100011 +
1/
10
12
b0000000000100100 5
b0000000000100011 6
b0000000000100011 7
18
1:
1;
1<
b0100011 =
#3700000000
0"
0&
02
08
0<
#3750000000
1"
b0000000000100101 %
1&
b0000000000100101 )
b0000000000100101 *
b0000000000100100 +
0/
00
12
b0000000000100101 5
b0000000000100100 6
b0000000000100100 7
18
0:
0;
1<
b0100100 =
#3800000000
0"
0&
02
08
0<
#3850000000
1"
b0000000000100110 %
1&
b0000000000100110 )
b0000000000100110 *
b0000000000100101 +
1/
10
12
b0000000000100110 5
b0000000000100101 6
b0000000000100101 7
18
1:
1;
1<
b0100101 =
#3900000000
0"
0&
02
08
0<
#3950000000
1"
b0000000000100111 %
1&
b0000000000100111 )
b0000000000100111 *
b0000000000100110 +
0/
00
12
b0000000000100111 5
b0000000000100110 6
b0000000000100110 7
18
0:
0;
1<
b0100110 =
#4000000000
0"
0&
02
08
0<
#4050000000
1"
b0000000000101000 %
1&
b0000000000101000 )
b0000000000101000 *
b0000000000100111 +
1/
10
12
b0000000000101000 5
b0000000000100111 6
b0000000000100111 7
18
1:
1;
1<
b0100111 =
#4100000000
0"
0&
02
08
0<
#4150000000
1"
b0000000000101001 %
1&
b0000000000101001 )
b0000000000101001 *
b0000000000101000 +
0/
00
12
b0000000000101001 5
b0000000000101000 6
b0000000000101000 7
18
0:
0;
1<
b0101000 =
#4200000000
0"
0&
02
08
0<
#4250000000
1"
b0000000000101010 %
1&
b0000000000101010 )
b0000000000101010 *
b0000000000101001 +
1/
10
12
b0000000000101010 5
b0000000000101001 6
b0000000000101001 7
18
1:
1;
1<
b0101001 =
#4300000000
0"
0&
02
08
0<
#4350000000
1"
b0000000000101011 %
1&
b0000000000101011 )
b0000000000101011 *
b0000000000101010 +
0/
00
12
b0000000000101011 5
b0000000000101010 6
b0000000000101010 7
18
0:
0;
1<
b0101010 =
#4400000000
0"
0&
02
08
0<
#4450000000
1"
b0000000000101100 %
1&
b0000000000101100 )
b0000000000101100 *
b0000000000101011 +
1/
10
12
b0000000000101100 5
b0000000000101011 6
b0000000000101011 7
18
1:
1;
1<
b0101011 =
#4500000000
0"
0&
02
08
0<
#4550000000
1"
b0000000000101101 %
1&
b0000000000101101 )
b0000000000101101 *
b0000000000101100 +
0/
00
12
b0000000000101101 5
b0000000000101100 6
b0000000000101100 7
18
0:
0;
1<
b0101100 =
#4600000000
0"
0&
02
08
0<
#4650000000
1"
b0000000000101110 %
1&
b0000000000101110 )
b0000000000101110 *
b0000000000101101 +
1/
10
12
b0000000000101110 5
b0000000000101101 6
b0000000000101101 7
18
1:
1;
1<
b0101101 =
#4700000000
0"
0&
02
08
0<
#4750000000
1"
b0000000000101111 %
1&
b0000000000101111 )
b0000000000101111 *
b0000000000101110 +
0/
00
12
b0000000000101111 5
b0000000000101110 6
b0000000000101110 7
18
0:
0;
1<
b0101110 =
#4800000000
0"
0&
02
08
0<
#4850000000
1"
b0000000000110000 %
1&
b0000000000110000 )
b0000000000110000 *
b0000000000101111 +
1/
10
12
b0000000000110000 5
b0000000000101111 6
b0000000000101111 7
18
1:
1;
1<
b0101111 =
#4900000000
0"
0&
02
08
0<
#4950000000
1"
b0000000000110001 %
1&
b0000000000110001 )
b0000000000110001 *
b0000000000110000 +
0/
00
12
b0000000000110001 5
b0000000000110000 6
b0000000000110000 7
18
0:
0;
1<
b0110000 =
#5000000000
0"
0&
02
08
0<
#5050000000
1"
b0000000000110010 %
1&
b0000000000110010 )
b0000000000110010 *
b0000000000110001 +
1/
10
12
b0000000000110010 5
b0000000000110001 6
b0000000000110001 7
18
1:
1;
1<
b0110001 =
#5100000000
0"
0&
02
08
0<
#5150000000
1"
b0000000000110011 %
1&
b0000000000110011 )
b0000000000110011 *
b0000000000110010 +
0/
00
12
b0000000000110011 5
b0000000000110010 6
b0000000000110010 7
18
0:
0;
1<
b0110010 =
#5200000000
0"
0&
02
08
0<
#5250000000
1"
b0000000000110100 %
1&
b0000000000110100 )
b0000000000110100 *
b0000000000110011 +
1/
10
12
b0000000000110100 5
b0000000000110011 6
b0000000000110011 7
18
1:
1;
1<
b0110011 =
#5300000000
0"
0&
02
08
0<
#5350000000
1"
b0000000000110101 %
1&
b0000000000110101 )
b0000000000110101 *
b0000000000110100 +
0/
00
12
b0000000000110101 5
b0000000000110100 6
b0000000000110100 7
18
0:
0;
1<
b0110100 =
#5400000000
0"
0&
02
08
0<
#5450000000
1"
b0000000000110110 %
1&
b0000000000110110 )
b0000000000110110 *
b0000000000110101 +
1/
10
12
b0000000000110110 5
b0000000000110101 6
b0000000000110101 7
18
1:
1;
1<
b0110101 =
#5500000000
0"
0&
02
08
0<
#5550000000
1"
b0000000000110111 %
1&
b0000000000110111 )
b0000000000110111 *
b0000000000110110 +
0/
00
12
b0000000000110111 5
b0000000000110110 6
b0000000000110110 7
18
0:
0;
1<
b0110110 =
#5600000000
0"
0&
02
08
0<
#5650000000
1"
b0000000000111000 %
1&
b0000000000111000 )
b0000000000111000 *
b0000000000110111 +
1/
10
12
b0000000000111000 5
b0000000000110111 6
b0000000000110111 7
18
1:
1;
1<
b0110111 =
#5700000000
0"
0&
02
08
0<
#5750000000
1"
b0000000000111001 %
1&
b0000000000111001 )
b0000000000111001 *
b0000000000111000 +
0/
00
12
b0000000000111001 5
b0000000000111000 6
b0000000000111000 7
18
0:
0;
1<
b0111000 =
#5800000000
0"
0&
02
08
0<
#5850000000
1"
b0000000000111010 %
1&
b0000000000111010 )
b0000000000111010 *
b0000000000111001 +
1/
10
12
b0000000000111010 5
b0000000000111001 6
b0000000000111001 7
18
1:
1;
1<
b0111001 =
#5900000000
0"
0&
02
08
0<
#5950000000
1"
b0000000000111011 %
1&
b0000000000111011 )
b0000000000111011 *
b0000000000111010 +
0/
00
12
b0000000000111011 5
b0000000000111010 6
b0000000000111010 7
18
0:
0;
1<
b0111010 =
#6000000000
0"
0&
02
08
0<
#6050000000
1"
b0000000000111100 %
1&
b0000000000111100 )
b0000000000111100 *
b0000000000111011 +
1/
10
12
b0000000000111100 5
b0000000000111011 6
b0000000000111011 7
18
1:
1;
1<
b0111011 =
#6100000000
0"
0&
02
08
0<
#6150000000
1"
b0000000000111101 %
1&
b0000000000111101 )
b0000000000111101 *
b0000000000111100 +
0/
00
12
b0000000000111101 5
b0000000000111100 6
b0000000000111100 7
18
0:
0;
1<
b0111100 =
#6200000000
0"
0&
02
08
0<
#6250000000
1"
b0000000000111110 %
1&
b0000000000111110 )
b0000000000111110 *
b0000000000111101 +
1/
10
12
b0000000000111110 5
b0000000000111101 6
b0000000000111101 7
18
1:
1;
1<
b0111101 =
#6300000000
0"
0&
02
08
0<
#6350000000
1"
b0000000000111111 %
1&
b0000000000111111 )
b0000000000111111 *
b0000000000111110 +
0/
00
12
b0000000000111111 5
b0000000000111110 6
b0000000000111110 7
18
0:
0;
1<
b0111110 =
#6400000000
0"
0&
02
08
0<
#6450000000
1"
b0000000001000000 %
1&
b0000000001000000 )
b0000000001000000 *
b0000000000111111 +
1/
10
12
b0000000001000000 5
b0000000000111111 6
b0000000000111111 7
18
1:
1;
1<
b0111111 =
#6500000000
0"
0&
02
08
0<
#6550000000
1"
b0000000001000001 %
1&
b0000000001000001 )
b0000000001000001 *
b0000000001000000 +
0/
00
12
b0000000001000001 5
b0000000001000000 6
b0000000001000000 7
18
0:
0;
1<
b1000000 =
#6600000000
0"
0&
02
08
0<
#6650000000
1"
b0000000001000010 %
1&
b0000000001000010 )
b0000000001000010 *
b0000000001000001 +
1/
10
12
b0000000001000010 5
b0000000001000001 6
b0000000001000001 7
18
1:
1;
1<
b1000001 =
#6700000000
0"
0&
02
08
0<
#6750000000
1"
b0000000001000011 %
1&
b0000000001000011 )
b0000000001000011 *
b0000000001000010 +
0/
00
12
b0000000001000011 5
b0000000001000010 6
b0000000001000010 7
18
0:
0;
1<
b1000010 =
#6800000000
0"
0&
02
08
0<
#6850000000
1"
b0000000001000100 %
1&
b0000000001000100 )
b0000000001000100 *
b0000000001000011 +
1/
10
12
b0000000001000100 5
b0000000001000011 6
b0000000001000011 7
18
1:
1;
1<
b1000011 =
#6900000000
0"
0&
02
08
0<
#6950000000
1"
b0000000001000101 %
1&
b0000000001000101 )
b0000000001000101 *
b0000000001000100 +
0/
00
12
b0000000001000101 5
b0000000001000100 6
b0000000001000100 7
18
0:
0;
1<
b1000100 =
#7000000000
0"
0&
02
08
0<
#7050000000
1"
b0000000001000110 %
1&
b0000000001000110 )
b0000000001000110 *
b0000000001000101 +
1/
10
12
b0000000001000110 5
b0000000001000101 6
b0000000001000101 7
18
1:
1;
1<
b1000101 =
#7100000000
0"
0&
02
08
0<
#7150000000
1"
b0000000001000111 %
1&
b0000000001000111 )
b0000000001000111 *
b0000000001000110 +
0/
00
12
b0000000001000111 5
b0000000001000110 6
b0000000001000110 7
18
0:
0;
1<
b1000110 =
#7200000000
0"
0&
02
08
0<
#7250000000
1"
b0000000001001000 %
1&
b0000000001001000 )
b0000000001001000 *
b0000000001000111 +
1/
10
12
b0000000001001000 5
b0000000001000111 6
b0000000001000111 7
18
1:
1;
1<
b1000111 =
#7300000000
0"
0&
02
08
0<
#7350000000
1"
b0000000001001001 %
1&
b0000000001001001 )
b0000000001001001 *
b0000000001001000 +
0/
00
12
b0000000001001001 5
b0000000001001000 6
b0000000001001000 7
18
0:
0;
1<
b1001000 =
#7400000000
0"
0&
02
08
0<
#7450000000
1"
b0000000001001010 %
1&
b0000000001001010 )
b0000000001001010 *
b0000000001001001 +
1/
10
12
b0000000001001010 5
b0000000001001001 6
b0000000001001001 7
18
1:
1;
1<
b1001001 =
#7500000000
0"
0&
02
08
0<
#7550000000
1"
b0000000001001011 %
1&
b0000000001001011 )
b0000000001001011 *
b0000000001001010 +
0/
00
12
b0000000001001011 5
b0000000001001010 6
b0000000001001010 7
18
0:
0;
1<
b1001010 =
#7600000000
0"
0&
02
08
0<
#7650000000
1"
b0000000001001100 %
1&
b0000000001001100 )
b0000000001001100 *
b0000000001001011 +
1/
10
12
b0000000001001100 5
b0000000001001011 6
b0000000001001011 7
18
1:
1;
1<
b1001011 =
#7700000000
0"
0&
02
08
0<
#7750000000
1"
b0000000001001101 %
1&
b0000000001001101 )
b0000000001001101 *
b0000000001001100 +
0/
00
12
b0000000001001101 5
b0000000001001100 6
b0000000001001100 7
18
0:
0;
1<
b1001100 =
#7800000000
0"
0&
02
08
0<
#7850000000
1"
b0000000001001110 %
1&
b0000000001001110 )
b0000000001001110 *
b0000000001001101 +
1/
10
12
b0000000001001110 5
b0000000001001101 6
b0000000001001101 7
18
1:
1;
1<
b1001101 =
#7900000000
0"
0&
02
08
0<
#7950000000
1"
b0000000001001111 %
1&
b0000000001001111 )
b0000000001001111 *
b0000000001001110 +
0/
00
12
b0000000001001111 5
b0000000001001110 6
b0000000001001110 7
18
0:
0;
1<
b1001110 =
#8000000000
0"
0&
02
08
0<
#8050000000
1"
b0000000001010000 %
1&
b0000000001010000 )
b0000000001010000 *
b0000000001001111 +
1/
10
12
b0000000001010000 5
b0000000001001111 6
b0000000001001111 7
18
1:
1;
1<
b1001111 =
#8100000000
0"
0&
02
08
0<
#8150000000
1"
b0000000001010001 %
1&
b0000000001010001 )
b0000000001010001 *
b0000000001010000 +
0/
00
12
b0000000001010001 5
b0000000001010000 6
b0000000001010000 7
18
0:
0;
1<
b1010000 =
#8200000000
0"
0&
02
08
0<
#8250000000
1"
b0000000001010010 %
1&
b0000000001010010 )
b0000000001010010 *
b0000000001010001 +
1/
10
12
b0000000001010010 5
b0000000001010001 6
b0000000001010001 7
18
1:
1;
1<
b1010001 =
#8300000000
0"
0&
02
08
0<
#8350000000
1"
b0000000001010011 %
1&
b0000000001010011 )
b0000000001010011 *
b0000000001010010 +
0/
00
12
b0000000001010011 5
b0000000001010010 6
b0000000001010010 7
18
0:
0;
1<
b1010010 =
#8400000000
0"
0&
02
08
0<
#8450000000
1"
b0000000001010100 %
1&
b0000000001010100 )
b0000000001010100 *
b0000000001010011 +
1/
10
12
b0000000001010100 5
b0000000001010011 6
b0000000001010011 7
18
1:
1;
1<
b1010011 =
#8500000000
0"
0&
02
08
0<
#8550000000
1"
b0000000001010101 %
1&
b0000000001010101 )
b0000000001010101 *
b0000000001010100 +
0/
00
12
b0000000001010101 5
b0000000001010100 6
b0000000001010100 7
18
0:
0;
1<
b1010100 =
#8600000000
0"
0&
02
08
0<
#8650000000
1"
b0000000001010110 %
1&
b0000000001010110 )
b0000000001010110 *
b0000000001010101 +
1/
10
12
b0000000001010110 5
b0000000001010101 6
b0000000001010101 7
18
1:
1;
1<
b1010101 =
#8700000000
0"
0&
02
08
0<
#8750000000
1"
b0000000001010111 %
1&
b0000000001010111 )
b0000000001010111 *
b0000000001010110 +
0/
00
12
b0000000001010111 5
b0000000001010110 6
b0000000001010110 7
18
0:
0;
1<
b1010110 =
#8800000000
0"
0&
02
08
0<
#8850000000
1"
b0000000001011000 %
1&
b0000000001011000 )
b0000000001011000 *
b0000000001010111 +
1/
10
12
b0000000001011000 5
b0000000001010111 6
b0000000001010111 7
18
1:
1;
1<
b1010111 =
#8900000000
0"
0&
02
08
0<
#8950000000
1"
b0000000001011001 %
1&
b0000000001011001 )
b0000000001011001 *
b0000000001011000 +
0/
00
12
b0000000001011001 5
b0000000001011000 6
b0000000001011000 7
18
0:
0;
1<
b1011000 =
#9000000000
0"
0&
02
08
0<
#9050000000
1"
b0000000001011010 %
1&
b0000000001011010 )
b0000000001011010 *
b0000000001011001 +
1/
10
12
b0000000001011010 5
b0000000001011001 6
b0000000001011001 7
18
1:
1;
1<
b1011001 =
#9100000000
0"
0&
02
08
0<
